Workbook

Sheet Form Responses 1
A1: Timestamp | B1: Email id | C1: Name | D1: Code | E1: Score | F1: Sent | G1: Error | H1: Contact number | I1: College | J1: Are you a member of Equinox ? | K1: Which module are you most interested in? | L1: What are your expectations from this course?
A2: 46167.553 | B2: ayush.biswas@iitg.ac.in | C2: Ayush Biswas | D2: ="AE-"&TEXT(ROW()-1,"0000") -> AE-0001 | E2: {=IFERROR(XLOOKUP(D2,'Astronomy 101 Week 1 Quiz (Resp'!F:F,'Astronomy 101 Week 1 Quiz (Resp'!E:E),0)} -> 0 | F2: YES | H2: 7439112615 | I2: IITG | J2: No | K2: Theoretical Module, Computational Module, Observational Module
A3: 46167.558 | B3: tejas.khanna@iitg.ac.in | C3: Tejas Khanna | D3: ="AE-"&TEXT(ROW()-1,"0000") -> AE-0002 | E3: {=IFERROR(XLOOKUP(D3,'Astronomy 101 Week 1 Quiz (Resp'!F:F,'Astronomy 101 Week 1 Quiz (Resp'!E:E),0)} -> 0 | F3: YES | H3: 9555039015 | I3: IITG | J3: No | K3: Theoretical Module, Computational Module
A4: 46167.559 | B4: theajantahajong01@gmail.com | C4: Ajanta Hajong | D4: ="AE-"&TEXT(ROW()-1,"0000") -> AE-0003 | E4: {=IFERROR(XLOOKUP(D4,'Astronomy 101 Week 1 Quiz (Resp'!F:F,'Astronomy 101 Week 1 Quiz (Resp'!E:E),0)} -> 0 | F4: YES | H4: 6000568353 | I4: Cotton University | J4: No | K4: Theoretical Module, Observational Module | L4: To learn some basics of astronomy
A5: 46167.567 | B5: m.jinay@iitg.ac.in | C5: Jinay Mehta | D5: ="AE-"&TEXT(ROW()-1,"0000") -> AE-0004 | E5: {=IFERROR(XLOOKUP(D5,'Astronomy 101 Week 1 Quiz (Resp'!F:F,'Astronomy 101 Week 1 Quiz (Resp'!E:E),0)} -> 44 | F5: YES | H5: 7575842118 | I5: IIT Guwahati | J5: No | K5: Theoretical Module, Computational Module, Observational Module
A6: 46167.571 | B6: s.spoorthi@iitg.ac.in | C6: Spoorthi | D6: ="AE-"&TEXT(ROW()-1,"0000") -> AE-0005 | E6: {=IFERROR(XLOOKUP(D6,'Astronomy 101 Week 1 Quiz (Resp'!F:F,'Astronomy 101 Week 1 Quiz (Resp'!E:E),0)} -> 34 | F6: YES | H6: 8088291584 | I6: IIT GUWAHATI | J6: Yes | K6: Theoretical Module, Computational Module, Observational Module | L6: To learn more about the universe and how to use computational methods
A7: 46167.572 | B7: v.sakshi@iitg.ac.in | C7: Sakshi Vatsa | D7: ="AE-"&TEXT(ROW()-1,"0000") -> AE-0006 | E7: {=IFERROR(XLOOKUP(D7,'Astronomy 101 Week 1 Quiz (Resp'!F:F,'Astronomy 101 Week 1 Quiz (Resp'!E:E),0)} -> 0 | F7: YES | H7: 9999084219 | I7: IIT Guwahati | J7: Yes | K7: Theoretical Module, Computational Module
A8: 46167.574 | B8: raushank1042@iitg.ac.in | C8: Raushan kumar | D8: ="AE-"&TEXT(ROW()-1,"0000") -> AE-0007 | E8: {=IFERROR(XLOOKUP(D8,'Astronomy 101 Week 1 Quiz (Resp'!F:F,'Astronomy 101 Week 1 Quiz (Resp'!E:E),0)} -> 0 | F8: YES | H8: 9279720376 | I8: Iitg | J8: No | K8: Theoretical Module, Computational Module, Observational Module
A9: 46167.575 | B9: h.pasari@iitg.ac.in | C9: Harsh Pasari | D9: ="AE-"&TEXT(ROW()-1,"0000") -> AE-0008 | E9: {=IFERROR(XLOOKUP(D9,'Astronomy 101 Week 1 Quiz (Resp'!F:F,'Astronomy 101 Week 1 Quiz (Resp'!E:E),0)} -> 0 | F9: YES | H9: 8767544954 | I9: IIT G | J9: No | K9: Computational Module, Observational Module | L9: Learn more about how to observer the night sky being a night sky photographer , and how are the various values calculated so accurately despite universe being so random and vast
A10: 46167.575 | B10: y.patel@iitg.ac.in | C10: Yashvardhan Patel | D10: ="AE-"&TEXT(ROW()-1,"0000") -> AE-0009 | E10: {=IFERROR(XLOOKUP(D10,'Astronomy 101 Week 1 Quiz (Resp'!F:F,'Astronomy 101 Week 1 Quiz (Resp'!E:E),0)} -> 39 | F10: YES | H10: 9928810449 | I10: IITG | J10: Yes | K10: Theoretical Module
A11: 46167.577 | B11: anjali.patel@iitg.ac.in | C11: Anjali Patel | D11: ="AE-"&TEXT(ROW()-1,"0000") -> AE-0010 | E11: {=IFERROR(XLOOKUP(D11,'Astronomy 101 Week 1 Quiz (Resp'!F:F,'Astronomy 101 Week 1 Quiz (Resp'!E:E),0)} -> 0 | F11: YES | H11: 9294548721 | I11: IIT Guwahati | J11: No | K11: Theoretical Module, Computational Module, Observational Module | L11: Learn something new and gain some knowledge in this field.
A12: 46167.577 | B12: manvendracharan9@gmail.com | C12: Manvendra Singh Charan | D12: ="AE-"&TEXT(ROW()-1,"0000") -> AE-0011 | E12: {=IFERROR(XLOOKUP(D12,'Astronomy 101 Week 1 Quiz (Resp'!F:F,'Astronomy 101 Week 1 Quiz (Resp'!E:E),0)} -> 27 | F12: YES | H12: 8118800749 | I12: IIT Guwahati | J12: Yes | K12: Computational Module, Observational Module | L12: .
A13: 46167.578 | B13: ashutosh.sharma1@iisi.iitg.ac.in | C13: Ashutosh Sharma | D13: ="AE-"&TEXT(ROW()-1,"0000") -> AE-0012 | E13: {=IFERROR(XLOOKUP(D13,'Astronomy 101 Week 1 Quiz (Resp'!F:F,'Astronomy 101 Week 1 Quiz (Resp'!E:E),0)} -> 0 | F13: YES | H13: 8000290081 | I13: MBM University Jodhpur | J13: No | K13: Computational Module, Observational Module | L13: To learn something new
A14: 46167.578 | B14: j.vidhi@iitg.ac.in | C14: Vidhi joshi | D14: ="AE-"&TEXT(ROW()-1,"0000") -> AE-0013 | E14: {=IFERROR(XLOOKUP(D14,'Astronomy 101 Week 1 Quiz (Resp'!F:F,'Astronomy 101 Week 1 Quiz (Resp'!E:E),0)} -> 11 | F14: YES | H14: 8982520245 | I14: IIT guwahati | J14: Yes | K14: Computational Module
A15: 46167.579 | B15: alokk4009@iitg.ac.in | C15: Alok Kumar | D15: ="AE-"&TEXT(ROW()-1,"0000") -> AE-0014 | E15: {=IFERROR(XLOOKUP(D15,'Astronomy 101 Week 1 Quiz (Resp'!F:F,'Astronomy 101 Week 1 Quiz (Resp'!E:E),0)} -> 44 | F15: YES | H15: 8840990927 | I15: IIT Guwahati | J15: No | K15: Computational Module, Observational Module
A16: 46167.582 | B16: shaurya.jain@iitg.ac.in | C16: Shaurya jain | D16: ="AE-"&TEXT(ROW()-1,"0000") -> AE-0015 | E16: {=IFERROR(XLOOKUP(D16,'Astronomy 101 Week 1 Quiz (Resp'!F:F,'Astronomy 101 Week 1 Quiz (Resp'!E:E),0)} -> 0 | F16: YES | H16: 7849852991 | I16: Iit guwahati | J16: No | K16: Theoretical Module, Computational Module, Observational Module | L16: To learn something new
A17: 46167.584 | B17: abhinavkrish222@gmail.com | C17: Abhinav Krishna L | D17: ="AE-"&TEXT(ROW()-1,"0000") -> AE-0016 | E17: {=IFERROR(XLOOKUP(D17,'Astronomy 101 Week 1 Quiz (Resp'!F:F,'Astronomy 101 Week 1 Quiz (Resp'!E:E),0)} -> 39 | F17: YES | H17: 8867400191 | I17: Iit guwahati | J17: Yes | K17: Theoretical Module, Computational Module, Observational Module
A18: 46167.584 | B18: ketans@iitg.ac.in | C18: Ketan Singh | D18: ="AE-"&TEXT(ROW()-1,"0000") -> AE-0017 | E18: {=IFERROR(XLOOKUP(D18,'Astronomy 101 Week 1 Quiz (Resp'!F:F,'Astronomy 101 Week 1 Quiz (Resp'!E:E),0)} -> 0 | F18: YES | H18: 7389985731 | I18: Indian Institute of Technology Guwahati | J18: No | K18: Theoretical Module, Computational Module, Observational Module
A19: 46167.586 | B19: kaurpsandhu07@gmail.com | C19: Parneet kaur | D19: ="AE-"&TEXT(ROW()-1,"0000") -> AE-0018 | E19: {=IFERROR(XLOOKUP(D19,'Astronomy 101 Week 1 Quiz (Resp'!F:F,'Astronomy 101 Week 1 Quiz (Resp'!E:E),0)} -> 39 | F19: YES | H19: 7014589274 | I19: Indian Institute of technology Guwahati | J19: No | K19: Theoretical Module, Computational Module | L19: I want to learn more about these things
A20: 46167.587 | B20: s.rebbapragada@iitg.ac.in | C20: Sruteesh Satya R | D20: ="AE-"&TEXT(ROW()-1,"0000") -> AE-0019 | E20: {=IFERROR(XLOOKUP(D20,'Astronomy 101 Week 1 Quiz (Resp'!F:F,'Astronomy 101 Week 1 Quiz (Resp'!E:E),0)} -> 0 | F20: YES | H20: 8897540718 | I20: IIT GUWAHATI | J20: Yes | K20: Computational Module
A21: 46167.588 | B21: t.tanisha@iitg.ac.in | C21: Tanisha Tembhare | D21: ="AE-"&TEXT(ROW()-1,"0000") -> AE-0020 | E21: {=IFERROR(XLOOKUP(D21,'Astronomy 101 Week 1 Quiz (Resp'!F:F,'Astronomy 101 Week 1 Quiz (Resp'!E:E),0)} -> 0 | F21: YES | H21: 9604877398 | I21: IIT GUWAHATI | J21: No | K21: Observational Module
A22: 46167.591 | B22: d.joyshmit@iitg.ac.in | C22: Joyshmit Das | D22: ="AE-"&TEXT(ROW()-1,"0000") -> AE-0021 | E22: {=IFERROR(XLOOKUP(D22,'Astronomy 101 Week 1 Quiz (Resp'!F:F,'Astronomy 101 Week 1 Quiz (Resp'!E:E),0)} -> 0 | F22: YES | H22: 9330397631 | I22: IIT Guwahati | J22: No | K22: Theoretical Module, Computational Module | L22: Want to learn how ml concepts are applied to astronomy
A23: 46167.591 | B23: ankan.halder@iitg.ac.in | C23: Ankan Halder | D23: ="AE-"&TEXT(ROW()-1,"0000") -> AE-0022 | E23: {=IFERROR(XLOOKUP(D23,'Astronomy 101 Week 1 Quiz (Resp'!F:F,'Astronomy 101 Week 1 Quiz (Resp'!E:E),0)} -> 0 | F23: YES | H23: 9474359410 | I23: IIT Guwahati | J23: No | K23: Theoretical Module, Observational Module | L23: Learn more about galaxy
A24: 46167.592 | B24: m.jayanth@iitg.ac.in | C24: Jayanth Mummana | D24: ="AE-"&TEXT(ROW()-1,"0000") -> AE-0023 | E24: {=IFERROR(XLOOKUP(D24,'Astronomy 101 Week 1 Quiz (Resp'!F:F,'Astronomy 101 Week 1 Quiz (Resp'!E:E),0)} -> 0 | F24: YES | H24: 7483195454 | I24: IIT Guwahati | J24: No | K24: Computational Module
A25: 46167.593 | B25: anshitakalawat@gmail.com | C25: Anshita Kalawat | D25: ="AE-"&TEXT(ROW()-1,"0000") -> AE-0024 | E25: {=IFERROR(XLOOKUP(D25,'Astronomy 101 Week 1 Quiz (Resp'!F:F,'Astronomy 101 Week 1 Quiz (Resp'!E:E),0)} -> 0 | F25: YES | H25: 9166070127 | I25: IIT Guwahati | J25: No | K25: Computational Module | L25: The computational aspect interests me a lot because it combines astronomy with Python, data analysis, and machine learning, which are highly valuable skills for research and problem-solving. Also , I will be able to learn about telescopes, astrophotography, and real astronomical observations
A26: 46167.594 | B26: ipshitagargbts@gmail.com | C26: Ipshita Garg | D26: ="AE-"&TEXT(ROW()-1,"0000") -> AE-0025 | E26: {=IFERROR(XLOOKUP(D26,'Astronomy 101 Week 1 Quiz (Resp'!F:F,'Astronomy 101 Week 1 Quiz (Resp'!E:E),0)} -> 0 | F26: YES | H26: 9828133998 | I26: IIT Guwahati | J26: Yes | K26: Theoretical Module, Observational Module | L26: To learn more about the universe, how to operate devices and participate in hackathons
A27: 46167.594 | B27: dspb.sr2023@gmail.com | C27: Devi Sri Priya | D27: ="AE-"&TEXT(ROW()-1,"0000") -> AE-0026 | E27: {=IFERROR(XLOOKUP(D27,'Astronomy 101 Week 1 Quiz (Resp'!F:F,'Astronomy 101 Week 1 Quiz (Resp'!E:E),0)} -> 22 | F27: YES | H27: 9441467276 | I27: IIT Guwahati | J27: No | K27: Observational Module | L27: To learn about the universe, things I always wonder about
A28: 46167.598 | B28: h.sinha@iitg.ac.in | C28: Hrishikesh sinha | D28: ="AE-"&TEXT(ROW()-1,"0000") -> AE-0027 | E28: {=IFERROR(XLOOKUP(D28,'Astronomy 101 Week 1 Quiz (Resp'!F:F,'Astronomy 101 Week 1 Quiz (Resp'!E:E),0)} -> 0 | F28: YES | H28: 9239565239 | I28: IIT GUWAHATI | J28: No | K28: Theoretical Module, Computational Module, Observational Module
A29: 46167.604 | B29: n.saumya@iitg.ac.in | C29: Saumya Nawandhar | D29: ="AE-"&TEXT(ROW()-1,"0000") -> AE-0028 | E29: {=IFERROR(XLOOKUP(D29,'Astronomy 101 Week 1 Quiz (Resp'!F:F,'Astronomy 101 Week 1 Quiz (Resp'!E:E),0)} -> 0 | F29: YES | H29: 7977815011 | I29: IIT Guwahati | J29: No | K29: Theoretical Module, Computational Module, Observational Module
A30: 46167.605 | B30: b.karishmita@iitg.ac.in | C30: Karishmita | D30: ="AE-"&TEXT(ROW()-1,"0000") -> AE-0029 | E30: {=IFERROR(XLOOKUP(D30,'Astronomy 101 Week 1 Quiz (Resp'!F:F,'Astronomy 101 Week 1 Quiz (Resp'!E:E),0)} -> 0 | F30: YES | H30: 8822462331 | I30: IIT Guwahati | J30: No | K30: Computational Module
A31: 46167.607 | B31: yuvrajs2264@gmail.com | C31: Yuvraj Singh | D31: ="AE-"&TEXT(ROW()-1,"0000") -> AE-0030 | E31: {=IFERROR(XLOOKUP(D31,'Astronomy 101 Week 1 Quiz (Resp'!F:F,'Astronomy 101 Week 1 Quiz (Resp'!E:E),0)} -> 0 | F31: YES | H31: 8866202885 | I31: IIT Guwahati | J31: No | K31: Theoretical Module
A32: 46167.608 | B32: adityaj4005@iitg.ac.in | C32: Aditya Jaiswal | D32: ="AE-"&TEXT(ROW()-1,"0000") -> AE-0031 | E32: {=IFERROR(XLOOKUP(D32,'Astronomy 101 Week 1 Quiz (Resp'!F:F,'Astronomy 101 Week 1 Quiz (Resp'!E:E),0)} -> 0 | F32: YES | H32: 9685382808 | I32: IIT Guwahati | J32: Yes | K32: Computational Module, Observational Module | L32: I want to explore space a lot and want to know the deep folded secret of space to mend my mind
A33: 46167.609 | B33: h.allu@iitg.ac.iin | C33: Allu Hemanth | D33: ="AE-"&TEXT(ROW()-1,"0000") -> AE-0032 | E33: {=IFERROR(XLOOKUP(D33,'Astronomy 101 Week 1 Quiz (Resp'!F:F,'Astronomy 101 Week 1 Quiz (Resp'!E:E),0)} -> 0 | F33: YES | H33: 8374294794 | I33: IIT Guwahati | J33: No | K33: Computational Module
A34: 46167.609 | B34: n.kinha@iitg.ac.in | C34: Nitin Kinha | D34: ="AE-"&TEXT(ROW()-1,"0000") -> AE-0033 | E34: {=IFERROR(XLOOKUP(D34,'Astronomy 101 Week 1 Quiz (Resp'!F:F,'Astronomy 101 Week 1 Quiz (Resp'!E:E),0)} -> 43 | F34: YES | H34: 9664368547 | I34: IIT GUWAHATI | J34: No | K34: Theoretical Module, Computational Module, Observational Module
A35: 46167.61 | B35: t.kritika@iitg.ac.in | C35: Kritika Tulsyan | D35: ="AE-"&TEXT(ROW()-1,"0000") -> AE-0034 | E35: {=IFERROR(XLOOKUP(D35,'Astronomy 101 Week 1 Quiz (Resp'!F:F,'Astronomy 101 Week 1 Quiz (Resp'!E:E),0)} -> 0 | F35: YES | H35: 6394937630 | I35: IITG | J35: No | K35: Observational Module | L35: To learn and explore the field of astronomy
A36: 46167.616 | B36: e.linga@iitg.ac.in | C36: LINGA RAJA E | D36: ="AE-"&TEXT(ROW()-1,"0000") -> AE-0035 | E36: {=IFERROR(XLOOKUP(D36,'Astronomy 101 Week 1 Quiz (Resp'!F:F,'Astronomy 101 Week 1 Quiz (Resp'!E:E),0)} -> 46 | F36: YES | H36: 9629645373 | I36: IITG | J36: No | K36: Computational Module, Observational Module
A37: 46167.62 | B37: j.savani@iitg.ac.in | C37: Jinen Jigneshbhai savani | D37: ="AE-"&TEXT(ROW()-1,"0000") -> AE-0036 | E37: {=IFERROR(XLOOKUP(D37,'Astronomy 101 Week 1 Quiz (Resp'!F:F,'Astronomy 101 Week 1 Quiz (Resp'!E:E),0)} -> 41 | F37: YES | H37: 9426656212 | I37: Iit guwahati | J37: No | K37: Theoretical Module, Observational Module
A38: 46167.622 | B38: mitalisahu678@gmail.com | C38: Mitali Sahu | D38: ="AE-"&TEXT(ROW()-1,"0000") -> AE-0037 | E38: {=IFERROR(XLOOKUP(D38,'Astronomy 101 Week 1 Quiz (Resp'!F:F,'Astronomy 101 Week 1 Quiz (Resp'!E:E),0)} -> 0 | F38: YES | H38: 9691120470 | I38: IIT Guwahati | J38: Yes | K38: Theoretical Module, Computational Module, Observational Module | L38: .
A39: 46167.624 | B39: m.bhatnagar@iitg.ac.in | C39: Manas bhatnagar | D39: ="AE-"&TEXT(ROW()-1,"0000") -> AE-0038 | E39: {=IFERROR(XLOOKUP(D39,'Astronomy 101 Week 1 Quiz (Resp'!F:F,'Astronomy 101 Week 1 Quiz (Resp'!E:E),0)} -> 0 | F39: YES | H39: 9317433450 | I39: IITG | J39: Yes | K39: Theoretical Module, Computational Module, Observational Module | L39: To learn exciting things and make a good base in astronomy
A40: 46167.635 | B40: v.pyata@iitg.ac.in | C40: Vipul reddy pyata | D40: ="AE-"&TEXT(ROW()-1,"0000") -> AE-0039 | E40: {=IFERROR(XLOOKUP(D40,'Astronomy 101 Week 1 Quiz (Resp'!F:F,'Astronomy 101 Week 1 Quiz (Resp'!E:E),0)} -> 30 | F40: YES | H40: 9396453012 | I40: IIT Guwahati | J40: No | K40: Theoretical Module, Computational Module, Observational Module | L40: My primary expectation from this summer course is to build a strong foundational knowledge in astronomy and astrophysics by engaging with all three modules. From the theoretical module, I hope to understand the core physics governing celestial bodies. Through the computational and observational modules, I expect to gain practical, hands-on experience with astronomical data analysis, programming tools, and telescope data interpretation. Ultimately, I want to use this comprehensive exposure to explore potential research opportunities and contribute meaningfully to the Equinox club's future initiatives.
A41: 46167.64 | B41: s.atharv@iitg.ac.in | C41: Atharv Soni | D41: ="AE-"&TEXT(ROW()-1,"0000") -> AE-0040 | E41: {=IFERROR(XLOOKUP(D41,'Astronomy 101 Week 1 Quiz (Resp'!F:F,'Astronomy 101 Week 1 Quiz (Resp'!E:E),0)} -> 0 | F41: YES | H41: 8920743909 | I41: Iitg | J41: No | K41: Theoretical Module, Computational Module, Observational Module
A42: 46167.64 | B42: b.parth@iitg.ac.in | C42: Parth Bhangriya | D42: ="AE-"&TEXT(ROW()-1,"0000") -> AE-0041 | E42: {=IFERROR(XLOOKUP(D42,'Astronomy 101 Week 1 Quiz (Resp'!F:F,'Astronomy 101 Week 1 Quiz (Resp'!E:E),0)} -> 0 | F42: YES | H42: 8209564239 | I42: IITG | J42: No | K42: Computational Module, Observational Module
A43: 46167.66 | B43: u.swayam@iitg.ac.in | C43: Swayam Upadhyaya | D43: ="AE-"&TEXT(ROW()-1,"0000") -> AE-0042 | E43: {=IFERROR(XLOOKUP(D43,'Astronomy 101 Week 1 Quiz (Resp'!F:F,'Astronomy 101 Week 1 Quiz (Resp'!E:E),0)} -> 0 | F43: YES | H43: 9707340930 | I43: IITG | J43: No | K43: Theoretical Module, Computational Module
A44: 46167.673 | B44: r.ekalavya@iitg.ac.in | C44: Ekalavya Rathore | D44: ="AE-"&TEXT(ROW()-1,"0000") -> AE-0043 | E44: {=IFERROR(XLOOKUP(D44,'Astronomy 101 Week 1 Quiz (Resp'!F:F,'Astronomy 101 Week 1 Quiz (Resp'!E:E),0)} -> 0 | F44: YES | H44: 7014003657 | I44: IIT Guwahati | J44: Yes | K44: Theoretical Module, Observational Module
A45: 46167.678 | B45: bl0679947@gmail.com | C45: Bibek Lama | D45: ="AE-"&TEXT(ROW()-1,"0000") -> AE-0044 | E45: {=IFERROR(XLOOKUP(D45,'Astronomy 101 Week 1 Quiz (Resp'!F:F,'Astronomy 101 Week 1 Quiz (Resp'!E:E),0)} -> 46 | F45: YES | H45: 9239001518 | I45: IIT Guwahati | J45: Yes | K45: Theoretical Module, Computational Module
A46: 46167.692 | B46: k.hetal@iitg.ac.in | C46: Hetal Koul | D46: ="AE-"&TEXT(ROW()-1,"0000") -> AE-0045 | E46: {=IFERROR(XLOOKUP(D46,'Astronomy 101 Week 1 Quiz (Resp'!F:F,'Astronomy 101 Week 1 Quiz (Resp'!E:E),0)} -> 42 | F46: YES | H46: 9469918820 | I46: Indian Institute of Technology, Guwahati | J46: Yes | K46: Theoretical Module, Computational Module, Observational Module
A47: 46167.698 | B47: syed.hassan@iitg.ac.in | C47: Aayed | D47: ="AE-"&TEXT(ROW()-1,"0000") -> AE-0046 | E47: {=IFERROR(XLOOKUP(D47,'Astronomy 101 Week 1 Quiz (Resp'!F:F,'Astronomy 101 Week 1 Quiz (Resp'!E:E),0)} -> 39 | F47: YES | H47: 7070883463 | I47: IITG | J47: Yes | K47: Observational Module
A48: 46167.724 | B48: r.amartya@op.iitg.ac.in | C48: Amartya Rishi | D48: ="AE-"&TEXT(ROW()-1,"0000") -> AE-0047 | E48: {=IFERROR(XLOOKUP(D48,'Astronomy 101 Week 1 Quiz (Resp'!F:F,'Astronomy 101 Week 1 Quiz (Resp'!E:E),0)} -> 0 | F48: YES | H48: 9661255684 | I48: IIT GUWAHATI | J48: No | K48: Theoretical Module, Observational Module | L48: To learn more about the space out there and observe.
A49: 46167.736 | B49: v.bheemavarapu@iitg.ac.in | C49: Vidhathri B | D49: ="AE-"&TEXT(ROW()-1,"0000") -> AE-0048 | E49: {=IFERROR(XLOOKUP(D49,'Astronomy 101 Week 1 Quiz (Resp'!F:F,'Astronomy 101 Week 1 Quiz (Resp'!E:E),0)} -> 44 | F49: YES | H49: 9063701484 | I49: IIT Guwahati | J49: Yes | K49: Theoretical Module, Computational Module, Observational Module
A50: 46167.741 | B50: n.gosavi@iitg.ac.in | C50: Soham Gosavi | D50: ="AE-"&TEXT(ROW()-1,"0000") -> AE-0049 | E50: {=IFERROR(XLOOKUP(D50,'Astronomy 101 Week 1 Quiz (Resp'!F:F,'Astronomy 101 Week 1 Quiz (Resp'!E:E),0)} -> 41 | F50: YES | H50: 9049571315 | I50: Indian Institute of Technology Guwahati | J50: No | K50: Theoretical Module, Computational Module, Observational Module
A51: 46167.754 | B51: k.gulshan@iitg.ac.in | C51: Gulshan kumar | D51: ="AE-"&TEXT(ROW()-1,"0000") -> AE-0050 | E51: {=IFERROR(XLOOKUP(D51,'Astronomy 101 Week 1 Quiz (Resp'!F:F,'Astronomy 101 Week 1 Quiz (Resp'!E:E),0)} -> 0 | F51: YES | H51: 7739098638 | I51: IITG | J51: No | K51: Theoretical Module, Computational Module, Observational Module
A52: 46167.757 | B52: Jaideep1020@iitg.ac.in | C52: Jaideep | D52: ="AE-"&TEXT(ROW()-1,"0000") -> AE-0051 | E52: {=IFERROR(XLOOKUP(D52,'Astronomy 101 Week 1 Quiz (Resp'!F:F,'Astronomy 101 Week 1 Quiz (Resp'!E:E),0)} -> 0 | F52: YES | H52: 8696692940 | I52: IIT G | J52: No | K52: Computational Module, Observational Module
A53: 46167.76 | B53: s.munda@iitg.ac.in | C53: Satish Kumar Munda | D53: ="AE-"&TEXT(ROW()-1,"0000") -> AE-0052 | E53: {=IFERROR(XLOOKUP(D53,'Astronomy 101 Week 1 Quiz (Resp'!F:F,'Astronomy 101 Week 1 Quiz (Resp'!E:E),0)} -> 0 | F53: YES | H53: 9142696275 | I53: IIT Guwahati | J53: No | K53: Computational Module, Observational Module
A54: 46167.787 | B54: abhishriya@iitg.ac.in | C54: Abhishriya Singh | D54: ="AE-"&TEXT(ROW()-1,"0000") -> AE-0053 | E54: {=IFERROR(XLOOKUP(D54,'Astronomy 101 Week 1 Quiz (Resp'!F:F,'Astronomy 101 Week 1 Quiz (Resp'!E:E),0)} -> 0 | F54: YES | H54: 9875853683 | I54: IIT Guwahati | J54: Yes | K54: Theoretical Module, Computational Module, Observational Module
A55: 46167.788 | B55: y.tamboli@iitg.ac.in | C55: Yash Tamboli | D55: ="AE-"&TEXT(ROW()-1,"0000") -> AE-0054 | E55: {=IFERROR(XLOOKUP(D55,'Astronomy 101 Week 1 Quiz (Resp'!F:F,'Astronomy 101 Week 1 Quiz (Resp'!E:E),0)} -> 44 | F55: YES | H55: 7498063055 | I55: IIT Guwahati | J55: Yes | K55: Computational Module
A56: 46167.789 | B56: y.saikia@iitg.ac.in | C56: Yuvraj Saikia | D56: ="AE-"&TEXT(ROW()-1,"0000") -> AE-0055 | E56: {=IFERROR(XLOOKUP(D56,'Astronomy 101 Week 1 Quiz (Resp'!F:F,'Astronomy 101 Week 1 Quiz (Resp'!E:E),0)} -> 34 | F56: YES | H56: 9706969976 | I56: Indian Institute of Technology Guwahati | J56: No | K56: Computational Module
A57: 46167.792 | B57: b.falak@iitg.ac.in | C57: Falak Baweja | D57: ="AE-"&TEXT(ROW()-1,"0000") -> AE-0056 | E57: {=IFERROR(XLOOKUP(D57,'Astronomy 101 Week 1 Quiz (Resp'!F:F,'Astronomy 101 Week 1 Quiz (Resp'!E:E),0)} -> 0 | F57: YES | H57: 9172632677 | I57: Indian Institute of Technology, Guwahati | J57: No | K57: Computational Module, Observational Module | L57: I hope to have great learnings and deepen my understanding and curiosity of astromony as well as the use of ml concepts in it.
A58: 46167.807 | B58: m.prarthana@iitg.ac.in | C58: Prarthana M | D58: ="AE-"&TEXT(ROW()-1,"0000") -> AE-0057 | E58: {=IFERROR(XLOOKUP(D58,'Astronomy 101 Week 1 Quiz (Resp'!F:F,'Astronomy 101 Week 1 Quiz (Resp'!E:E),0)} -> 0 | F58: YES | H58: 9444927162 | I58: IIT Guwahati | J58: No | K58: Theoretical Module, Computational Module, Observational Module | L58: different timings for different courses
A59: 46167.818 | B59: s.samantray@iitg.ac.in | C59: Shreyas Samantray | D59: ="AE-"&TEXT(ROW()-1,"0000") -> AE-0058 | E59: {=IFERROR(XLOOKUP(D59,'Astronomy 101 Week 1 Quiz (Resp'!F:F,'Astronomy 101 Week 1 Quiz (Resp'!E:E),0)} -> 41 | F59: YES | H59: 7674053888 | I59: IIT Guwahati | J59: Yes | K59: Theoretical Module, Observational Module
A60: 46167.829 | B60: r.monalisha@iitg.ac.in | C60: MONALISHA RABHA | D60: ="AE-"&TEXT(ROW()-1,"0000") -> AE-0059 | E60: {=IFERROR(XLOOKUP(D60,'Astronomy 101 Week 1 Quiz (Resp'!F:F,'Astronomy 101 Week 1 Quiz (Resp'!E:E),0)} -> 43 | F60: YES | H60: 9387069293 | I60: IIT Guwahati | J60: Yes | K60: Observational Module | L60: to learn more about Astronomy
A61: 46167.879 | B61: mayank.arya@iitg.ac.in | C61: Mayank Arya | D61: ="AE-"&TEXT(ROW()-1,"0000") -> AE-0060 | E61: {=IFERROR(XLOOKUP(D61,'Astronomy 101 Week 1 Quiz (Resp'!F:F,'Astronomy 101 Week 1 Quiz (Resp'!E:E),0)} -> 0 | F61: YES | H61: 9661393965 | I61: IIT Guwahati | J61: Yes | K61: Theoretical Module, Computational Module, Observational Module
A62: 46167.889 | B62: toiyeb.ahangar@iitg.ac.in | C62: Toiyeb Ashiq Ahangar | D62: ="AE-"&TEXT(ROW()-1,"0000") -> AE-0061 | E62: {=IFERROR(XLOOKUP(D62,'Astronomy 101 Week 1 Quiz (Resp'!F:F,'Astronomy 101 Week 1 Quiz (Resp'!E:E),0)} -> 9 | F62: YES | H62: 9796701028 | I62: IIT Guwahati | J62: Yes | K62: Computational Module, Observational Module
A63: 46167.895 | B63: s.asolakr@iitg.ac.in | C63: Ganesh Sambhaji Asolkar | D63: ="AE-"&TEXT(ROW()-1,"0000") -> AE-0062 | E63: {=IFERROR(XLOOKUP(D63,'Astronomy 101 Week 1 Quiz (Resp'!F:F,'Astronomy 101 Week 1 Quiz (Resp'!E:E),0)} -> 0 | F63: YES | H63: 9552372063 | I63: IIT Guwahati | J63: Yes | K63: Computational Module
A64: 46167.904 | B64: vsamarth926@gmail.com | C64: Samarth Varshney | D64: ="AE-"&TEXT(ROW()-1,"0000") -> AE-0063 | E64: {=IFERROR(XLOOKUP(D64,'Astronomy 101 Week 1 Quiz (Resp'!F:F,'Astronomy 101 Week 1 Quiz (Resp'!E:E),0)} -> 0 | F64: YES | H64: 7579931539 | I64: Aligarh college of engineering and technology | J64: No | K64: Computational Module | L64: To enhance my knowledge…
A65: 46167.928 | B65: navamikhatmode@gmail.com | C65: Navami Santosh Khatmode | D65: ="AE-"&TEXT(ROW()-1,"0000") -> AE-0064 | E65: {=IFERROR(XLOOKUP(D65,'Astronomy 101 Week 1 Quiz (Resp'!F:F,'Astronomy 101 Week 1 Quiz (Resp'!E:E),0)} -> 0 | F65: YES | H65: 8788270374 | I65: IIT Guwahati | J65: Yes | K65: Computational Module, Observational Module
A66: 46167.948 | B66: ayushk4022@iitg.ac.in | C66: Ayush Kumar | D66: ="AE-"&TEXT(ROW()-1,"0000") -> AE-0065 | E66: {=IFERROR(XLOOKUP(D66,'Astronomy 101 Week 1 Quiz (Resp'!F:F,'Astronomy 101 Week 1 Quiz (Resp'!E:E),0)} -> 0 | F66: YES | H66: 9369820561 | I66: Indian institute of technology Guwahati | J66: No | K66: Theoretical Module, Computational Module, Observational Module | L66: Learning
A67: 46167.966 | B67: sachink3085@iitg.ac.in | C67: Sachin kumar | D67: ="AE-"&TEXT(ROW()-1,"0000") -> AE-0066 | E67: {=IFERROR(XLOOKUP(D67,'Astronomy 101 Week 1 Quiz (Resp'!F:F,'Astronomy 101 Week 1 Quiz (Resp'!E:E),0)} -> 0 | F67: YES | H67: 6207129700 | I67: IIT Guwahati | J67: Yes | K67: Computational Module, Observational Module
A68: 46167.992 | B68: kaustubh.patil@iitg.ac.in | C68: Kaustubh Patil | D68: ="AE-"&TEXT(ROW()-1,"0000") -> AE-0067 | E68: {=IFERROR(XLOOKUP(D68,'Astronomy 101 Week 1 Quiz (Resp'!F:F,'Astronomy 101 Week 1 Quiz (Resp'!E:E),0)} -> 0 | F68: YES | H68: 9321154399 | I68: IIT Guwahati | J68: No | K68: Theoretical Module, Computational Module, Observational Module | L68: Gain experience
A69: 46168.011 | B69: g.yuvraj@iitg.ac.in | C69: Yuvraj Gupta | D69: ="AE-"&TEXT(ROW()-1,"0000") -> AE-0068 | E69: {=IFERROR(XLOOKUP(D69,'Astronomy 101 Week 1 Quiz (Resp'!F:F,'Astronomy 101 Week 1 Quiz (Resp'!E:E),0)} -> 0 | F69: YES | H69: 9257943628 | I69: IITGuwahati | J69: Yes | K69: Computational Module, Observational Module
A70: 46168.023 | B70: archit.singal@iitg.ac.in | C70: Archit Singal | D70: ="AE-"&TEXT(ROW()-1,"0000") -> AE-0069 | E70: {=IFERROR(XLOOKUP(D70,'Astronomy 101 Week 1 Quiz (Resp'!F:F,'Astronomy 101 Week 1 Quiz (Resp'!E:E),0)} -> 45 | F70: YES | H70: 6283639868 | I70: Indian Institute of Technology Guwahati | J70: Yes | K70: Computational Module, Observational Module
A71: 46168.476 | B71: t.chandana@iitg.ac.in | C71: Tatikonda Chandana | D71: ="AE-"&TEXT(ROW()-1,"0000") -> AE-0070 | E71: {=IFERROR(XLOOKUP(D71,'Astronomy 101 Week 1 Quiz (Resp'!F:F,'Astronomy 101 Week 1 Quiz (Resp'!E:E),0)} -> 0 | F71: YES | H71: 8142806087 | I71: IIT GUWAHATI | J71: No | K71: Theoretical Module, Computational Module, Observational Module | L71: To get deep into astronomy, to observe more than starry sky and explore different aspects of the sky. And also to get hands on experience in computational work in astronomy
A72: 46168.86 | B72: k.gulshan@iitg.ac.in | C72: Gulshan Kumar | D72: ="AE-"&TEXT(ROW()-1,"0000") -> AE-0071 | E72: {=IFERROR(XLOOKUP(D72,'Astronomy 101 Week 1 Quiz (Resp'!F:F,'Astronomy 101 Week 1 Quiz (Resp'!E:E),0)} -> 0 | F72: YES | H72: 7739098638 | I72: IITG | J72: No | K72: Theoretical Module, Computational Module, Observational Module
A73: 46168.98 | B73: sayedaymaan28@gmail.com | C73: Sayed Aymaan | D73: ="AE-"&TEXT(ROW()-1,"0000") -> AE-0072 | E73: {=IFERROR(XLOOKUP(D73,'Astronomy 101 Week 1 Quiz (Resp'!F:F,'Astronomy 101 Week 1 Quiz (Resp'!E:E),0)} -> 0 | F73: YES | H73: 7326086433 | I73: NIT Rourkela | J73: No | K73: Theoretical Module, Observational Module
A74: 46168.991 | B74: omprasad2105@gmail.com | C74: Omprasad Sahoo | D74: ="AE-"&TEXT(ROW()-1,"0000") -> AE-0073 | E74: {=IFERROR(XLOOKUP(D74,'Astronomy 101 Week 1 Quiz (Resp'!F:F,'Astronomy 101 Week 1 Quiz (Resp'!E:E),0)} -> 0 | F74: YES | H74: 6370058700 | I74: National Institute of Technology, Rourkela | J74: No | K74: Theoretical Module
A75: 46168.994 | B75: siddhapatra87@gmail.com | C75: Siddha Narayan Patra | D75: ="AE-"&TEXT(ROW()-1,"0000") -> AE-0074 | E75: {=IFERROR(XLOOKUP(D75,'Astronomy 101 Week 1 Quiz (Resp'!F:F,'Astronomy 101 Week 1 Quiz (Resp'!E:E),0)} -> 0 | F75: YES | H75: 8895617835 | I75: NIT Rourkela | J75: No | K75: Theoretical Module, Computational Module, Observational Module | L75: I am expecting that by the end of this course I would have learnt the programming skills required to combine observational data and theoretical knowledge to draw meaningful conclusions about the nature of the cosmos.
A76: 46169.032 | B76: shravani0744@gmail.com | C76: Shravani Anil Jadhav | D76: ="AE-"&TEXT(ROW()-1,"0000") -> AE-0075 | E76: {=IFERROR(XLOOKUP(D76,'Astronomy 101 Week 1 Quiz (Resp'!F:F,'Astronomy 101 Week 1 Quiz (Resp'!E:E),0)} -> 0 | F76: YES | H76: 9920845248 | I76: National Institute of Technology Calicut | J76: No | K76: Computational Module, Observational Module | L76: I hope this course helps me get stronger in my computational skills and to see how it connects to real world problems.
A77: 46169.053 | B77: singhiti105@gmail.com | C77: Iti singh | D77: ="AE-"&TEXT(ROW()-1,"0000") -> AE-0076 | E77: {=IFERROR(XLOOKUP(D77,'Astronomy 101 Week 1 Quiz (Resp'!F:F,'Astronomy 101 Week 1 Quiz (Resp'!E:E),0)} -> 46 | F77: YES | H77: 9981303770 | I77: Maulana Azad national institute of technology bhopal | J77: No | K77: Computational Module | L77: I have an affinity towards input of data science in the field of astronomy, as an ardent engineering student, the more I engage in the application of data science the more alluring it feels and I hope this course will help me to be a consummate person in this field by providing me a holistic view and conscientious towards computational module.
A78: 46169.065 | B78: solapurkarchaitanya@gmail.com | C78: Chaitanya Rao Solapurkar | D78: ="AE-"&TEXT(ROW()-1,"0000") -> AE-0077 | E78: {=IFERROR(XLOOKUP(D78,'Astronomy 101 Week 1 Quiz (Resp'!F:F,'Astronomy 101 Week 1 Quiz (Resp'!E:E),0)} -> 0 | F78: YES | H78: 9630808399 | I78: MANIT, Bhopal | J78: No | K78: Theoretical Module, Computational Module | L78: Learning something I've always had an interest in and apply it to create things....
A79: 46169.066 | B79: rajharsh3871@gmail.com | C79: HARSH KUMAR | D79: ="AE-"&TEXT(ROW()-1,"0000") -> AE-0078 | E79: {=IFERROR(XLOOKUP(D79,'Astronomy 101 Week 1 Quiz (Resp'!F:F,'Astronomy 101 Week 1 Quiz (Resp'!E:E),0)} -> 0 | F79: YES | H79: 9431255973 | I79: The LNM Institute of Information Technology, Jaipur | J79: No | K79: Theoretical Module, Computational Module, Observational Module
A80: 46169.068 | B80: devanshkatariya13@gmail.com | C80: Devansh Katariya | D80: ="AE-"&TEXT(ROW()-1,"0000") -> AE-0079 | E80: {=IFERROR(XLOOKUP(D80,'Astronomy 101 Week 1 Quiz (Resp'!F:F,'Astronomy 101 Week 1 Quiz (Resp'!E:E),0)} -> 0 | F80: YES | H80: 7387166279 | I80: LNMIIT | J80: No | K80: Theoretical Module, Observational Module | L80: To increase my knowledge in astrophotography
A81: 46169.074 | B81: imnishant2008@gmail.com | C81: Nishant Sharma | D81: ="AE-"&TEXT(ROW()-1,"0000") -> AE-0080 | E81: {=IFERROR(XLOOKUP(D81,'Astronomy 101 Week 1 Quiz (Resp'!F:F,'Astronomy 101 Week 1 Quiz (Resp'!E:E),0)} -> 0 | F81: YES | H81: 9501889938 | I81: LNMIIT | J81: No | K81: Computational Module
A82: 46169.093 | B82: jivyajain4062006@gmail.com | C82: Jivya Jain | D82: ="AE-"&TEXT(ROW()-1,"0000") -> AE-0081 | E82: {=IFERROR(XLOOKUP(D82,'Astronomy 101 Week 1 Quiz (Resp'!F:F,'Astronomy 101 Week 1 Quiz (Resp'!E:E),0)} -> 0 | F82: YES | H82: 7597209911 | I82: LNMIIT | J82: No | K82: Theoretical Module, Computational Module, Observational Module
A83: 46169.094 | B83: 06freyag@gmail.com | C83: Tejasi Gaur | D83: ="AE-"&TEXT(ROW()-1,"0000") -> AE-0082 | E83: {=IFERROR(XLOOKUP(D83,'Astronomy 101 Week 1 Quiz (Resp'!F:F,'Astronomy 101 Week 1 Quiz (Resp'!E:E),0)} -> 0 | F83: YES | H83: 9109059666 | I83: MANIT, Bhopal | J83: No | K83: Theoretical Module, Computational Module | L83: Understanding the fundamentals of our universe and astronomy and learning the use of ML and data analysis in astronomy- gaining working knowledge and a deep understanding of it.
A84: 46169.129 | B84: theanegi10@gmail.com | C84: Thea Negi | D84: ="AE-"&TEXT(ROW()-1,"0000") -> AE-0083 | E84: {=IFERROR(XLOOKUP(D84,'Astronomy 101 Week 1 Quiz (Resp'!F:F,'Astronomy 101 Week 1 Quiz (Resp'!E:E),0)} -> 44 | F84: YES | H84: 9870444706 | I84: IIT Guwahati | J84: No
A85: 46169.221 | B85: 25ucs125@lnmiit.ac.in | C85: Ayush agarwal | D85: ="AE-"&TEXT(ROW()-1,"0000") -> AE-0084 | E85: {=IFERROR(XLOOKUP(D85,'Astronomy 101 Week 1 Quiz (Resp'!F:F,'Astronomy 101 Week 1 Quiz (Resp'!E:E),0)} -> 0 | F85: YES | H85: 6377863683 | I85: LNMIIT | J85: No | K85: Observational Module
A86: 46169.253 | B86: vanshika.kamal@iitg.ac.in | C86: Vanshika Kamal | D86: ="AE-"&TEXT(ROW()-1,"0000") -> AE-0085 | E86: {=IFERROR(XLOOKUP(D86,'Astronomy 101 Week 1 Quiz (Resp'!F:F,'Astronomy 101 Week 1 Quiz (Resp'!E:E),0)} -> 0 | F86: YES | H86: 9460008400 | I86: IITG | J86: No | K86: Theoretical Module, Computational Module, Observational Module | L86: I just want to learn something new from this course
A87: 46169.284 | B87: yerragudishivani@gmail.com | C87: Sivani yerragudi | D87: ="AE-"&TEXT(ROW()-1,"0000") -> AE-0086 | E87: {=IFERROR(XLOOKUP(D87,'Astronomy 101 Week 1 Quiz (Resp'!F:F,'Astronomy 101 Week 1 Quiz (Resp'!E:E),0)} -> 0 | F87: YES | H87: 8520826757 | I87: NIT BHOPAL | J87: No | K87: Observational Module | L87: I want to improve my photography skills
A88: 46169.32 | B88: nishthajain897@gmail.com | C88: Nishtha | D88: ="AE-"&TEXT(ROW()-1,"0000") -> AE-0087 | E88: {=IFERROR(XLOOKUP(D88,'Astronomy 101 Week 1 Quiz (Resp'!F:F,'Astronomy 101 Week 1 Quiz (Resp'!E:E),0)} -> 0 | F88: YES | H88: 9413844456 | I88: LNMIIT | J88: No | K88: Theoretical Module, Computational Module
A89: 46169.333 | B89: suryawanshikamlesh18@gmail.com | C89: Kamlesh suryawanshi | D89: ="AE-"&TEXT(ROW()-1,"0000") -> AE-0088 | E89: {=IFERROR(XLOOKUP(D89,'Astronomy 101 Week 1 Quiz (Resp'!F:F,'Astronomy 101 Week 1 Quiz (Resp'!E:E),0)} -> 0 | F89: YES | H89: 8109517118 | I89: Maulana Azad National Institute of Technology Bhopal | J89: No | K89: Computational Module | L89: To learn something new that I don't know
A90: 46169.346 | B90: rakshandar.dd24.ph@nitp.ac.in | C90: Rakshanda Razi | D90: ="AE-"&TEXT(ROW()-1,"0000") -> AE-0089 | E90: {=IFERROR(XLOOKUP(D90,'Astronomy 101 Week 1 Quiz (Resp'!F:F,'Astronomy 101 Week 1 Quiz (Resp'!E:E),0)} -> 45 | F90: YES | H90: 9942169891 | I90: National Institute of Technology Patna | J90: No | K90: Theoretical Module, Computational Module, Observational Module | L90: I expect this course to help me build a strong foundation in astronomy while improving my computational and observational skills. I am excited to learn about astrophysics, Python-based data analysis, telescope handling, and astrophotography through both theory and practical experience.
A91: 46169.351 | B91: aditi.yadav@iitg.ac.in | C91: Aditi yadav | D91: ="AE-"&TEXT(ROW()-1,"0000") -> AE-0090 | E91: {=IFERROR(XLOOKUP(D91,'Astronomy 101 Week 1 Quiz (Resp'!F:F,'Astronomy 101 Week 1 Quiz (Resp'!E:E),0)} -> 0 | F91: YES | H91: 8168339952 | I91: Iit guwahati | J91: No | K91: Theoretical Module, Observational Module
A92: 46169.367 | B92: sukanyau2121@gmail.com | C92: Sukanya | D92: ="AE-"&TEXT(ROW()-1,"0000") -> AE-0091 | E92: {=IFERROR(XLOOKUP(D92,'Astronomy 101 Week 1 Quiz (Resp'!F:F,'Astronomy 101 Week 1 Quiz (Resp'!E:E),0)} -> 0 | F92: YES | H92: 8303492872 | I92: IIT Guwahati | J92: No | K92: Computational Module
A93: 46169.375 | B93: drisya_b241440ed@nitc.ac.in | C93: DRISYA J | D93: ="AE-"&TEXT(ROW()-1,"0000") -> AE-0092 | E93: {=IFERROR(XLOOKUP(D93,'Astronomy 101 Week 1 Quiz (Resp'!F:F,'Astronomy 101 Week 1 Quiz (Resp'!E:E),0)} -> 0 | F93: YES | H93: 9072938160 | I93: National Institute of Technology calicut | J93: No | K93: Theoretical Module, Computational Module
A94: 46169.387 | B94: deepaliimishra111@gmail.com | C94: Deepali Mishra | D94: ="AE-"&TEXT(ROW()-1,"0000") -> AE-0093 | E94: {=IFERROR(XLOOKUP(D94,'Astronomy 101 Week 1 Quiz (Resp'!F:F,'Astronomy 101 Week 1 Quiz (Resp'!E:E),0)} -> 0 | F94: YES | H94: 7428485611 | I94: National Institute Of Technology Patna | J94: No | K94: Computational Module | L94: To learn something new.
A95: 46169.397 | B95: 25111011132@stu.manit.ac.in | C95: Arnav Tiwari | D95: ="AE-"&TEXT(ROW()-1,"0000") -> AE-0094 | E95: {=IFERROR(XLOOKUP(D95,'Astronomy 101 Week 1 Quiz (Resp'!F:F,'Astronomy 101 Week 1 Quiz (Resp'!E:E),0)} -> 33 | F95: YES | H95: 7415576490 | I95: Maulana Azad national institute of technology | J95: No | K95: Theoretical Module, Observational Module | L95: To learn more about astronomy and space related topics
A96: 46169.398 | B96: arthavibhati@gmail.com | C96: Arthavi Bhati | D96: ="AE-"&TEXT(ROW()-1,"0000") -> AE-0095 | E96: {=IFERROR(XLOOKUP(D96,'Astronomy 101 Week 1 Quiz (Resp'!F:F,'Astronomy 101 Week 1 Quiz (Resp'!E:E),0)} -> 44 | F96: YES | H96: 8999457297 | I96: Maulana Azad National Institute of Technology, Bhopal | J96: No | K96: Theoretical Module | L96: To learn more about Astronomy and gain knowledge. This is a platform that'll help me become more efficient in a field that is very rare for students to master in.
A97: 46169.406 | B97: roshanchenglei@gmail.com | C97: Khundongbam Roshan Chenglei | D97: ="AE-"&TEXT(ROW()-1,"0000") -> AE-0096 | E97: {=IFERROR(XLOOKUP(D97,'Astronomy 101 Week 1 Quiz (Resp'!F:F,'Astronomy 101 Week 1 Quiz (Resp'!E:E),0)} -> 0 | F97: YES | H97: 9774525452 | I97: Bangalore University | J97: No | K97: Theoretical Module, Computational Module, Observational Module
A98: 46169.406 | B98: sivada_b241454ed@nitc.ac.in | C98: Sivada S | D98: ="AE-"&TEXT(ROW()-1,"0000") -> AE-0097 | E98: {=IFERROR(XLOOKUP(D98,'Astronomy 101 Week 1 Quiz (Resp'!F:F,'Astronomy 101 Week 1 Quiz (Resp'!E:E),0)} -> 0 | F98: YES | H98: 9495692653 | I98: NIT Calicut | J98: No | K98: Theoretical Module, Observational Module
A99: 46169.407 | B99: anagha_b241431ed@nitc.ac.in | C99: Anagha Ak | D99: ="AE-"&TEXT(ROW()-1,"0000") -> AE-0098 | E99: {=IFERROR(XLOOKUP(D99,'Astronomy 101 Week 1 Quiz (Resp'!F:F,'Astronomy 101 Week 1 Quiz (Resp'!E:E),0)} -> 38 | F99: YES | H99: 9074737289 | I99: National institute of technology, Calicut | J99: No | K99: Theoretical Module | L99: To know more about astronomy
A100: 46169.411 | B100: shinthaheibihaobijam1@gmail.com | C100: Shinthaheibi Haobijam | D100: ="AE-"&TEXT(ROW()-1,"0000") -> AE-0099 | E100: {=IFERROR(XLOOKUP(D100,'Astronomy 101 Week 1 Quiz (Resp'!F:F,'Astronomy 101 Week 1 Quiz (Resp'!E:E),0)} -> 0 | F100: YES | H100: 9366573924 | I100: DM College of Science | J100: No | K100: Theoretical Module, Computational Module, Observational Module | L100: To learn new things
...

Sheet Astronomy 101 Week 1 Quiz (Resp
A1: Timestamp | B1: Email Address | C1: Score | D1: Assignment Instructions Open the Colab notebook using the link below and create a copy in your Google Drive. Complete all the tasks/questions in the notebook. Once finished, make sure the sharing settings are set to "Anyone with the link can view" and paste the shareable link to your completed notebook in the response field below. Colab Notebook Link: https://colab.research.google.com/drive/1TMEWLkX_CKyG5EeCCwjXskLidoTfA4a9?usp=sharing Submission: Paste the link to your completed notebook below. | E1: Final Score | F1: Astronomy 101 Code: | G1: Name: | H1: Email id | I1: Contact Number | J1: If astronomers discovered that galaxies were moving toward us rather than away from us, how would that fundamentally change the interpretation of the following theory? | K1: For a significant portion of its early history (the Photon Epoch), the universe is described as an opaque 'soup' or fog. What key conceptual shift allowed the universe to finally become transparent to light, creating the cosmic background radiation we observe today? | L1: According to the standard Big Bang timeline, what specific fundamental force separation is hypothesised to have triggered the period of rapid exponential expansion known as cosmic inflation? | M1: During the 'Dark Ages', the universe was filled with a sea of neutral hydrogen atoms that made the cosmos opaque to shorter wavelengths of light. What mechanism fundamentally altered this state, ending the Dark Ages and allowing starlight to travel vast distances? | N1: What does the following images symbolise based on the image and time of the event | O1: Why does the Cosmic Microwave Background (CMB) appear to have a 'perfect' thermal spectrum despite space being essentially empty today? | P1: What is the fundamental difference between the 'R-process' and 'S-process' in neutron capture? | Q1: During the brief period of Big Bang nucleosynthesis, why did the universe primarily produce hydrogen and helium, rather than fusing all primordial matter into heavier, ultra-stable elements like iron? | R1: Olbers' Paradox historically asked why the night sky is dark if the universe is infinite and filled with stars. How does the Big Bang model elegantly resolve this paradox? | S1: How do neutron star mergers overcome the electrostatic repulsion that prevents standard fusion? | T1: Why are lithium, beryllium, and boron produced via cosmic ray collisions (fission) rather than typical stellar fusion? | U1: All elements are products of stardust. Do you agree? | V1: How does the birth of massive, early stars actively influence the formation of subsequent structures in the early universe? | W1: During the formation of a star, why does the inner region of the collapsing gas cloud eventually cease to collapse further and temporarily stabilize as a protostar? | X1: Identify what is present in the following image | Y1: How did the initial state of the universe during the period of quantum fluctuations ultimately dictate the large-scale distribution of matter we observe today? | Z1: In the context of large-scale galactic structures, what defines the boundaries of the "Laniakea" Supercluster, our cosmic home? | AA1: The majority of the universe's total volume is composed of what specific structural feature within the Cosmic Web? | AB1: Dark matter is an essential component of the universe's mass-energy density. Why is it impossible to observe dark matter directly using conventional optical or radio telescopes? | AC1: In contemporary physics, what is the primary observed macroscopic effect attributed to Dark Energy? | AD1: In an attempt to explain the anomalous rotation curves of galaxies without invoking unseen dark matter particles, physicists developed an alternative theory known as M.O.N.D. What does this acronym signify? | AE1: Before a star like our Sun formally initiates nuclear fusion, it spends millions of years in the "T Tauri" phase. During this pre-main-sequence stage, what is the primary source of the star's immense heat and luminosity? | AF1: Astronomers frequently measure the abundance of the element Lithium to determine the precise age of a T Tauri star. Why does the observable amount of Lithium decrease as the star ages? | AG1: What specific event definitively marks the end of the T Tauri phase and the beginning of a star's stable life on the "main sequence"? | AH1: Where do the vast majority of the universe's exceptionally heavy elements, such as gold, silver, and uranium, originate? | AI1: When an exceptionally massive star exhausts its nuclear fuel, its core violently collapses. If the remaining core mass dramatically exceeds the Tolman-Oppenheimer-Volkoff limit, what is the resulting celestial object? | AJ1: During the very early universe, a quantum process known as baryogenesis resulted in a crucial asymmetry. What was the ultimate outcome of this statistical anomaly? | AK1: If you are standing at the North Pole, where would the celestial pole be located in your sky? | AL1: Why do observers at different latitudes on Earth see the celestial pole at different heights above the horizon? | AM1: You are trying to show a friend all the different constellation drawings that are currently above your head, but Stellarium keeps making them disappear, only showing the single constellation in the middle of your screen. How do you fix this? | AN1: You want to find out what phase the moon was in on the exact night you were born. How do you achieve this in Stellarium? | AO1: Identify the following solar position | AP1: Why did the Indian Institute of Astrophysics find it necessary to establish an observatory in the Himalayan region, such as the one at Hanle, rather than relying exclusively on their existing southern observatories? | AQ1: According to the documentary in day 5, how does the creation of the Hanle Dark Sky Reserve benefit the local ecosystem, specifically the wildlife? | AR1: What will be the output of the following code? a = (1, 2, [3, 4]) a[2].append(5) print(a) | AS1: What will be the output? x = [1, 2, 3] y = x y += [4] print(x) | AT1: Which of the following can be used as a dictionary key? | AU1: What will be the output of the following code? d = {} d[(1, 2)] = "A" d[(1, 2, [3, 4])] = "B" print(len(d)) | AV1: What will be the output of the following code? a = [1, 2, 3] b = a a = a + [4] print(b) | AW1: When we tried capturing The solar position at noon for a year, what pattern did it symbolise? | AX1: Imagine you are observing the night sky from the northern hemisphere. Why are the constellations located near the summer solstice in the ecliptic path best viewed during the winter months? | AY1: Our modern map of constellations is a flat projection of a celestial sphere. What is the primary consequence of this method on the appearance of constellations at the extreme north and south poles of the map? | AZ1: Why is it often easier for a beginner to identify Jupiter in the night sky compared to Mercury? | BA1: If you were an ancient observer tracking a specific 'wandering star' that seemed to travel forward, pause, and then move backwards over several months, which celestial body would you most likely be observing? | BB1: Why is the concept of "integrated magnitude" important when observing objects like galaxies or nebulae through a telescope compared to point-like stars? | BC1: If astrology enthusiasts base their horoscopes on the zodiac, why is it scientifically misaligned with current reality?
A2: 46179.656 | B2: buralagan9@gmail.com | C2: 37 | D2: https://colab.research.google.com/drive/110-WzL0SE8DlazI8Gbo6sCxpV9Vjuc_-?usp=sharing | E2: =VALUE(LEFT(C2,FIND("/",C2)-1))+IF(D2<>"",5,0) -> 42 | F2: AE-0752 | G2: Lagan Bura | H2: buralagan9@gmail.com | I2: 9896334843 | J2: It would confirm a cyclic universe model. | K2: The cooling of the universe allowed ionized nuclei to capture electrons, neutralizing their charge and stopping them from constantly scattering photons. | L2: The separation of gravity from the unified forces at the end of the Planck Epoch. | N2: A: Merger of two galaxies during early galaxy formation B: Black Hole Formation | O2: It is the leftover light emitted by a hot, dense plasma that permeated the entire universe roughly 400,000 years after the Big Bang. | P2: The R-process involves rapid neutron accumulation before decay, leading to larger jumps in atomic mass compared to the slower S-process | R2: The universe is not infinitely old, meaning light from the most distant stars has simply not had enough time to reach us. | S2: The merger releases a massive amount of neutrons, which are then captured by atomic nuclei (the 'R-process') | T2: Because stars reach temperatures that immediately destroy these specific elements | U2: Yes, because hydrogen and helium were primarily formed during the Big Bang which later went on to become stars where other elements were created. | V2: They produce radiation that strips electrons from surrounding gas, promoting further star formation through collisions. | W2: The temperature rises until the outward kinetic energy of the gas balances the inward gravitational pull. | X2: Our home supercluster - Laniakea | Y2: Random energy spawnings caused matter to clump together, a pattern that magnified as the universe expanded. | Z2: B) A basin of attraction where the peculiar velocities of galaxies are directed inward toward a common gravitational focal point. | AA2: C) Cosmic voids, which are vast regions nearly empty of galaxies. | AB2: C) It does not interact via the electromagnetic force, meaning it neither emits, absorbs, nor reflects light. | AC2: B) It drives the accelerating, exponential expansion of the universe on large scales. | AD2: C) Modified Newtonian Dynamics | AE2: B) Gravitational energy released as the massive cloud of gas continuously contracts under its own weight. | AF2: B) Rapid rotation and convective currents drag the Lithium into the deep, hot interior of the star where it is destroyed by nuclear reactions. | AG2: D) The initiation of sustained hydrogen-to-helium nuclear fusion in the star's core. | AH2: C) They are formed during the cataclysmic explosions of supernovae and the violent mergers of neutron stars. | AI2: C) A black hole | AJ2: B) The creation of slightly more matter than antimatter (roughly one extra per billion), allowing the material universe to exist. | AK2: A) At your zenith (directly overhead). | AL2: C) Because the angle of the celestial pole correlates to the observer's latitude on the globe. | AM2: Long-press the constellations button in the bottom left and turn off the 'Centered Only' setting. | AN2: Tap the time in the bottom right, open the precise time controls, enter your birth date and time, and then locate the Moon. | AO2: Summer Solstice Sunrise | AP2: The monsoon clouds heavily affect southern India, forcing observatories to shut down for months, whereas the Himalayan ranges block these clouds, providing consistently clear skies. | AQ2: It helps preserve the natural navigation cues for migratory birds, which can otherwise be easily confused by bright artificial lighting. | AR2: (1, 2, [3, 4, 5]) | AS2: [1, 2, 3, 4] | AT2: (1, 2) | AU2: Error | AV2: [1, 2, 3] | AW2: 8 pattern | AX2: B) The sun obscures the summer solstice constellations during the summer, but during the winter, the night side of the Earth faces them. | AY2: A) They appear significantly stretched out horizontally compared to how they actually look in the night sky. | AZ2: B) Jupiter appears high in the dark night sky and is exceptionally bright, whereas Mercury is only visible very close to the horizon during sunrise or sunset and is often hidden by clouds. | BA2: C) Mars | BB2: B) Because the light of non-point objects is spread over an area, which can make them appear dimmer than their total magnitude suggests.
A3: 46179.661 | B3: varundevsr07@gmail.com | C3: 39 | E3: =VALUE(LEFT(C3,FIND("/",C3)-1))+IF(D3<>"",5,0) -> 39 | F3: AE-0999 | G3: Varun Dev S R | H3: varundevsr07@gmail.com | I3: 9400881978 | J3: It would disprove the idea that the universe originated from a single point. | K3: The cooling of the universe allowed ionized nuclei to capture electrons, neutralizing their charge and stopping them from constantly scattering photons. | L3: The separation of gravity from the unified forces at the end of the Planck Epoch. | N3: A: A Supermassive Black Hole Merger B: Black Hole Formation | O3: It is the leftover light emitted by a hot, dense plasma that permeated the entire universe roughly 400,000 years after the Big Bang. | P3: The R-process involves rapid neutron accumulation before decay, leading to larger jumps in atomic mass compared to the slower S-process | R3: The universe is not infinitely old, meaning light from the most distant stars has simply not had enough time to reach us. | S3: The merger releases a massive amount of neutrons, which are then captured by atomic nuclei (the 'R-process') | T3: Because stellar fusion processes skip over them due to their position on the binding energy curve, making them harder to fuse | U3: No, because Only elements like carbon, oxygen, neon, silicon, iron, etc. are formed from stellar synthesis except which all other elements are not directly products of stardust. | V3: They produce radiation that strips electrons from surrounding gas, promoting further star formation through collisions. | W3: The temperature rises until the outward kinetic energy of the gas balances the inward gravitational pull. | X3: Our home supercluster - Laniakea | Y3: Random energy spawnings caused matter to clump together, a pattern that magnified as the universe expanded. | Z3: B) A basin of attraction where the peculiar velocities of galaxies are directed inward toward a common gravitational focal point. | AA3: C) Cosmic voids, which are vast regions nearly empty of galaxies. | AB3: C) It does not interact via the electromagnetic force, meaning it neither emits, absorbs, nor reflects light. | AC3: B) It drives the accelerating, exponential expansion of the universe on large scales. | AD3: C) Modified Newtonian Dynamics | AE3: B) Gravitational energy released as the massive cloud of gas continuously contracts under its own weight. | AF3: B) Rapid rotation and convective currents drag the Lithium into the deep, hot interior of the star where it is destroyed by nuclear reactions. | AG3: D) The initiation of sustained hydrogen-to-helium nuclear fusion in the star's core. | AH3: C) They are formed during the cataclysmic explosions of supernovae and the violent mergers of neutron stars. | AI3: C) A black hole | AJ3: B) The creation of slightly more matter than antimatter (roughly one extra per billion), allowing the material universe to exist. | AK3: A) At your zenith (directly overhead). | AL3: C) Because the angle of the celestial pole correlates to the observer's latitude on the globe. | AM3: Long-press the constellations button in the bottom left and turn off the 'Centered Only' setting. | AN3: Tap the time in the bottom right, open the precise time controls, enter your birth date and time, and then locate the Moon. | AO3: Winter Solstice Sunrise | AP3: The monsoon clouds heavily affect southern India, forcing observatories to shut down for months, whereas the Himalayan ranges block these clouds, providing consistently clear skies. | AQ3: It helps preserve the natural navigation cues for migratory birds, which can otherwise be easily confused by bright artificial lighting. | AR3: (1, 2, [3, 4, 5]) | AS3: [1, 2, 3, 4] | AT3: (1, 2) | AU3: Error | AV3: [1, 2, 3] | AW3: 8 pattern | AX3: B) The sun obscures the summer solstice constellations during the summer, but during the winter, the night side of the Earth faces them. | AY3: A) They appear significantly stretched out horizontally compared to how they actually look in the night sky. | AZ3: B) Jupiter appears high in the dark night sky and is exceptionally bright, whereas Mercury is only visible very close to the horizon during sunrise or sunset and is often hidden by clouds. | BA3: C) Mars | BB3: B) Because the light of non-point objects is spread over an area, which can make them appear dimmer than their total magnitude suggests.
A4: 46179.663 | B4: kp9781204@gmail.com | C4: 40 | D4: https://colab.research.google.com/drive/1j7Y4coPArrJNJUoiKyHOp2C7ulHpD06I?usp=sharing | E4: =VALUE(LEFT(C4,FIND("/",C4)-1))+IF(D4<>"",5,0) -> 45 | F4: AE-0729 | G4: Kusambh Prasad | H4: kp9781204@gmail.com | I4: 6204371419 | J4: It would disprove the idea that the universe originated from a single point. | K4: The cooling of the universe allowed ionized nuclei to capture electrons, neutralizing their charge and stopping them from constantly scattering photons. | L4: The separation of gravity from the unified forces at the end of the Planck Epoch. | N4: A: Merger of two galaxies during early galaxy formation B: Black Hole Formation | O4: It is the leftover light emitted by a hot, dense plasma that permeated the entire universe roughly 400,000 years after the Big Bang. | P4: The R-process involves rapid neutron accumulation before decay, leading to larger jumps in atomic mass compared to the slower S-process | R4: The universe is not infinitely old, meaning light from the most distant stars has simply not had enough time to reach us. | S4: The merger releases a massive amount of neutrons, which are then captured by atomic nuclei (the 'R-process') | T4: Because stellar fusion processes skip over them due to their position on the binding energy curve, making them harder to fuse | U4: No, because Only elements like carbon, oxygen, neon, silicon, iron, etc. are formed from stellar synthesis except which all other elements are not directly products of stardust. | V4: They produce radiation that strips electrons from surrounding gas, promoting further star formation through collisions. | W4: The temperature rises until the outward kinetic energy of the gas balances the inward gravitational pull. | X4: Our home supercluster - Laniakea | Y4: Random energy spawnings caused matter to clump together, a pattern that magnified as the universe expanded. | Z4: B) A basin of attraction where the peculiar velocities of galaxies are directed inward toward a common gravitational focal point. | AA4: C) Cosmic voids, which are vast regions nearly empty of galaxies. | AB4: C) It does not interact via the electromagnetic force, meaning it neither emits, absorbs, nor reflects light. | AC4: B) It drives the accelerating, exponential expansion of the universe on large scales. | AD4: C) Modified Newtonian Dynamics | AE4: B) Gravitational energy released as the massive cloud of gas continuously contracts under its own weight. | AF4: B) Rapid rotation and convective currents drag the Lithium into the deep, hot interior of the star where it is destroyed by nuclear reactions. | AG4: D) The initiation of sustained hydrogen-to-helium nuclear fusion in the star's core. | AH4: C) They are formed during the cataclysmic explosions of supernovae and the violent mergers of neutron stars. | AI4: C) A black hole | AJ4: B) The creation of slightly more matter than antimatter (roughly one extra per billion), allowing the material universe to exist. | AK4: A) At your zenith (directly overhead). | AL4: C) Because the angle of the celestial pole correlates to the observer's latitude on the globe. | AM4: Long-press the constellations button in the bottom left and turn off the 'Centered Only' setting. | AN4: Tap the time in the bottom right, open the precise time controls, enter your birth date and time, and then locate the Moon. | AO4: Summer Solstice Sunrise | AP4: The monsoon clouds heavily affect southern India, forcing observatories to shut down for months, whereas the Himalayan ranges block these clouds, providing consistently clear skies. | AQ4: It helps preserve the natural navigation cues for migratory birds, which can otherwise be easily confused by bright artificial lighting. | AR4: (1, 2, [3, 4, 5]) | AS4: [1, 2, 3, 4] | AT4: (1, 2) | AU4: Error | AV4: [1, 2, 3] | AW4: 8 pattern | AX4: B) The sun obscures the summer solstice constellations during the summer, but during the winter, the night side of the Earth faces them. | AY4: A) They appear significantly stretched out horizontally compared to how they actually look in the night sky. | AZ4: B) Jupiter appears high in the dark night sky and is exceptionally bright, whereas Mercury is only visible very close to the horizon during sunrise or sunset and is often hidden by clouds. | BA4: C) Mars | BB4: B) Because the light of non-point objects is spread over an area, which can make them appear dimmer than their total magnitude suggests.
A5: 46179.677 | B5: namratau855@gmail.com | C5: 39 | D5: https://colab.research.google.com/drive/1H4HUGFM_DWFW4GKDAIXHREt_VrHxREhy?usp=sharing | E5: =VALUE(LEFT(C5,FIND("/",C5)-1))+IF(D5<>"",5,0) -> 44 | F5: AE-0976 | G5: Namrata Upadhyay | H5: namratau855@gmail.com | I5: 7394841804 | J5: It would disprove the idea that the universe originated from a single point. | K5: The cooling of the universe allowed ionized nuclei to capture electrons, neutralizing their charge and stopping them from constantly scattering photons. | L5: The separation of the strong nuclear force from the electroweak force. | N5: A: A Supermassive Black Hole Merger B: Black Hole Formation | O5: It is the leftover light emitted by a hot, dense plasma that permeated the entire universe roughly 400,000 years after the Big Bang. | P5: The R-process involves rapid neutron accumulation before decay, leading to larger jumps in atomic mass compared to the slower S-process | R5: The universe is not infinitely old, meaning light from the most distant stars has simply not had enough time to reach us. | S5: The merger releases a massive amount of neutrons, which are then captured by atomic nuclei (the 'R-process') | T5: Because stellar fusion processes skip over them due to their position on the binding energy curve, making them harder to fuse | U5: Yes, because hydrogen and helium were primarily formed during the Big Bang which later went on to become stars where other elements were created. | V5: They produce radiation that strips electrons from surrounding gas, promoting further star formation through collisions. | W5: The temperature rises until the outward kinetic energy of the gas balances the inward gravitational pull. | X5: Our home supercluster - Laniakea | Y5: Random energy spawnings caused matter to clump together, a pattern that magnified as the universe expanded. | Z5: B) A basin of attraction where the peculiar velocities of galaxies are directed inward toward a common gravitational focal point. | AA5: C) Cosmic voids, which are vast regions nearly empty of galaxies. | AB5: C) It does not interact via the electromagnetic force, meaning it neither emits, absorbs, nor reflects light. | AC5: B) It drives the accelerating, exponential expansion of the universe on large scales. | AD5: C) Modified Newtonian Dynamics | AE5: B) Gravitational energy released as the massive cloud of gas continuously contracts under its own weight. | AF5: B) Rapid rotation and convective currents drag the Lithium into the deep, hot interior of the star where it is destroyed by nuclear reactions. | AG5: D) The initiation of sustained hydrogen-to-helium nuclear fusion in the star's core. | AH5: C) They are formed during the cataclysmic explosions of supernovae and the violent mergers of neutron stars. | AI5: C) A black hole | AJ5: B) The creation of slightly more matter than antimatter (roughly one extra per billion), allowing the material universe to exist. | AK5: A) At your zenith (directly overhead). | AL5: C) Because the angle of the celestial pole correlates to the observer's latitude on the globe. | AM5: Long-press the constellations button in the bottom left and turn off the 'Centered Only' setting. | AN5: Tap the time in the bottom right, open the precise time controls, enter your birth date and time, and then locate the Moon. | AO5: Equinox Sunrise | AP5: The monsoon clouds heavily affect southern India, forcing observatories to shut down for months, whereas the Himalayan ranges block these clouds, providing consistently clear skies. | AQ5: It helps preserve the natural navigation cues for migratory birds, which can otherwise be easily confused by bright artificial lighting. | AR5: (1, 2, [3, 4, 5]) | AS5: [1, 2, 3, 4] | AT5: (1, 2) | AU5: Error | AV5: [1, 2, 3] | AW5: ∞ pattrn | AX5: B) The sun obscures the summer solstice constellations during the summer, but during the winter, the night side of the Earth faces them. | AY5: A) They appear significantly stretched out horizontally compared to how they actually look in the night sky. | AZ5: B) Jupiter appears high in the dark night sky and is exceptionally bright, whereas Mercury is only visible very close to the horizon during sunrise or sunset and is often hidden by clouds. | BA5: C) Mars | BB5: B) Because the light of non-point objects is spread over an area, which can make them appear dimmer than their total magnitude suggests.
A6: 46179.689 | B6: surya280907@gmail.com | C6: 25 | E6: =VALUE(LEFT(C6,FIND("/",C6)-1))+IF(D6<>"",5,0) -> 25 | F6: AE-0985 | G6: Surya S P | H6: surya280907@gmail.com | I6: 8122217371 | J6: It would have no impact on the Big Bang theory. | K6: The cooling of the universe allowed ionized nuclei to capture electrons, neutralizing their charge and stopping them from constantly scattering photons. | L6: The separation of the strong nuclear force from the electroweak force. | N6: A: A Supermassive Black Hole Merger B: Black Hole Formation | O6: It is the leftover light emitted by a hot, dense plasma that permeated the entire universe roughly 400,000 years after the Big Bang. | P6: The R-process involves rapid neutron accumulation before decay, leading to larger jumps in atomic mass compared to the slower S-process | R6: The universe is not infinitely old, meaning light from the most distant stars has simply not had enough time to reach us. | S6: The merger releases a massive amount of neutrons, which are then captured by atomic nuclei (the 'R-process') | T6: Because stellar fusion processes skip over them due to their position on the binding energy curve, making them harder to fuse | U6: Yes, because hydrogen and helium were primarily formed during the Big Bang which later went on to become stars where other elements were created. | V6: They produce radiation that strips electrons from surrounding gas, promoting further star formation through collisions. | W6: The temperature rises until the outward kinetic energy of the gas balances the inward gravitational pull. | X6: Our home supercluster - Laniakea | Y6: Random energy spawnings caused matter to clump together, a pattern that magnified as the universe expanded. | Z6: B) A basin of attraction where the peculiar velocities of galaxies are directed inward toward a common gravitational focal point. | AA6: C) Cosmic voids, which are vast regions nearly empty of galaxies. | AB6: C) It does not interact via the electromagnetic force, meaning it neither emits, absorbs, nor reflects light. | AC6: B) It drives the accelerating, exponential expansion of the universe on large scales. | AD6: C) Modified Newtonian Dynamics | AE6: B) Gravitational energy released as the massive cloud of gas continuously contracts under its own weight. | AF6: B) Rapid rotation and convective currents drag the Lithium into the deep, hot interior of the star where it is destroyed by nuclear reactions. | AG6: D) The initiation of sustained hydrogen-to-helium nuclear fusion in the star's core. | AH6: C) They are formed during the cataclysmic explosions of supernovae and the violent mergers of neutron stars. | AI6: C) A black hole | AJ6: B) The creation of slightly more matter than antimatter (roughly one extra per billion), allowing the material universe to exist. | AR6: (1, 2, [3, 4, 5]) | AS6: [1, 2, 3, 4] | AT6: {"a": 1} | AU6: Error | AV6: [1, 2, 3]
A7: 46179.705 | B7: dhairya1101@iitg.ac.in | C7: 41 | D7: https://colab.research.google.com/drive/1-pucxgA-o-cF20V9SC3gz5FXclCvMVuk?usp=sharing | E7: =VALUE(LEFT(C7,FIND("/",C7)-1))+IF(D7<>"",5,0) -> 46 | F7: AE-0265 | G7: Dhairya | H7: dhairya1101@iitg.ac.in | I7: 8630225566 | J7: It would disprove the idea that the universe originated from a single point. | K7: The cooling of the universe allowed ionized nuclei to capture electrons, neutralizing their charge and stopping them from constantly scattering photons. | L7: The separation of the strong nuclear force from the electroweak force. | N7: A: Merger of two galaxies during early galaxy formation B: Black Hole Formation | O7: It is the leftover light emitted by a hot, dense plasma that permeated the entire universe roughly 400,000 years after the Big Bang. | P7: The R-process involves rapid neutron accumulation before decay, leading to larger jumps in atomic mass compared to the slower S-process | R7: The universe is not infinitely old, meaning light from the most distant stars has simply not had enough time to reach us. | S7: The merger releases a massive amount of neutrons, which are then captured by atomic nuclei (the 'R-process') | T7: Because stellar fusion processes skip over them due to their position on the binding energy curve, making them harder to fuse | U7: No, because Only elements like carbon, oxygen, neon, silicon, iron, etc. are formed from stellar synthesis except which all other elements are not directly products of stardust. | V7: They produce radiation that strips electrons from surrounding gas, promoting further star formation through collisions. | W7: The temperature rises until the outward kinetic energy of the gas balances the inward gravitational pull. | X7: Our home supercluster - Laniakea | Y7: Random energy spawnings caused matter to clump together, a pattern that magnified as the universe expanded. | Z7: B) A basin of attraction where the peculiar velocities of galaxies are directed inward toward a common gravitational focal point. | AA7: C) Cosmic voids, which are vast regions nearly empty of galaxies. | AB7: C) It does not interact via the electromagnetic force, meaning it neither emits, absorbs, nor reflects light. | AC7: B) It drives the accelerating, exponential expansion of the universe on large scales. | AD7: C) Modified Newtonian Dynamics | AE7: B) Gravitational energy released as the massive cloud of gas continuously contracts under its own weight. | AF7: B) Rapid rotation and convective currents drag the Lithium into the deep, hot interior of the star where it is destroyed by nuclear reactions. | AG7: D) The initiation of sustained hydrogen-to-helium nuclear fusion in the star's core. | AH7: C) They are formed during the cataclysmic explosions of supernovae and the violent mergers of neutron stars. | AI7: C) A black hole | AJ7: B) The creation of slightly more matter than antimatter (roughly one extra per billion), allowing the material universe to exist. | AK7: A) At your zenith (directly overhead). | AL7: C) Because the angle of the celestial pole correlates to the observer's latitude on the globe. | AM7: Long-press the constellations button in the bottom left and turn off the 'Centered Only' setting. | AN7: Tap the time in the bottom right, open the precise time controls, enter your birth date and time, and then locate the Moon. | AO7: Equinox Sunrise | AP7: The monsoon clouds heavily affect southern India, forcing observatories to shut down for months, whereas the Himalayan ranges block these clouds, providing consistently clear skies. | AQ7: It helps preserve the natural navigation cues for migratory birds, which can otherwise be easily confused by bright artificial lighting. | AR7: (1, 2, [3, 4, 5]) | AS7: [1, 2, 3, 4] | AT7: (1, 2) | AU7: Error | AV7: [1, 2, 3] | AW7: ∞ pattrn | AX7: B) The sun obscures the summer solstice constellations during the summer, but during the winter, the night side of the Earth faces them. | AY7: A) They appear significantly stretched out horizontally compared to how they actually look in the night sky. | AZ7: B) Jupiter appears high in the dark night sky and is exceptionally bright, whereas Mercury is only visible very close to the horizon during sunrise or sunset and is often hidden by clouds. | BA7: C) Mars | BB7: B) Because the light of non-point objects is spread over an area, which can make them appear dimmer than their total magnitude suggests.
A8: 46179.709 | B8: jinumehta12@gmail.com | C8: 39 | D8: https://colab.research.google.com/drive/1Fb5fobzOQ_J6oXX-UCAyHwfbvzB6XomE?usp=sharing | E8: =VALUE(LEFT(C8,FIND("/",C8)-1))+IF(D8<>"",5,0) -> 44 | F8: AE-0004 | G8: Jinay Mehta | H8: m.jinay@iitg.ac.in | I8: 7575842118 | J8: It would disprove the idea that the universe originated from a single point. | K8: The cooling of the universe allowed ionized nuclei to capture electrons, neutralizing their charge and stopping them from constantly scattering photons. | L8: The separation of the strong nuclear force from the electroweak force. | N8: A: Merger of two galaxies during early galaxy formation B: Death of a star | O8: It is the leftover light emitted by a hot, dense plasma that permeated the entire universe roughly 400,000 years after the Big Bang. | P8: The R-process involves rapid neutron accumulation before decay, leading to larger jumps in atomic mass compared to the slower S-process | R8: The universe is not infinitely old, meaning light from the most distant stars has simply not had enough time to reach us. | S8: The merger releases a massive amount of neutrons, which are then captured by atomic nuclei (the 'R-process') | T8: Because stellar fusion processes skip over them due to their position on the binding energy curve, making them harder to fuse | U8: Yes, because hydrogen and helium were primarily formed during the Big Bang which later went on to become stars where other elements were created. | V8: They produce radiation that strips electrons from surrounding gas, promoting further star formation through collisions. | W8: The temperature rises until the outward kinetic energy of the gas balances the inward gravitational pull. | X8: Our home supercluster - Laniakea | Y8: Random energy spawnings caused matter to clump together, a pattern that magnified as the universe expanded. | Z8: B) A basin of attraction where the peculiar velocities of galaxies are directed inward toward a common gravitational focal point. | AA8: C) Cosmic voids, which are vast regions nearly empty of galaxies. | AB8: C) It does not interact via the electromagnetic force, meaning it neither emits, absorbs, nor reflects light. | AC8: B) It drives the accelerating, exponential expansion of the universe on large scales. | AD8: C) Modified Newtonian Dynamics | AE8: B) Gravitational energy released as the massive cloud of gas continuously contracts under its own weight. | AF8: B) Rapid rotation and convective currents drag the Lithium into the deep, hot interior of the star where it is destroyed by nuclear reactions. | AG8: D) The initiation of sustained hydrogen-to-helium nuclear fusion in the star's core. | AH8: C) They are formed during the cataclysmic explosions of supernovae and the violent mergers of neutron stars. | AI8: C) A black hole | AJ8: B) The creation of slightly more matter than antimatter (roughly one extra per billion), allowing the material universe to exist. | AK8: A) At your zenith (directly overhead). | AL8: C) Because the angle of the celestial pole correlates to the observer's latitude on the globe. | AM8: Long-press the constellations button in the bottom left and turn off the 'Centered Only' setting. | AN8: Tap the time in the bottom right, open the precise time controls, enter your birth date and time, and then locate the Moon. | AO8: Equinox Sunrise | AP8: The monsoon clouds heavily affect southern India, forcing observatories to shut down for months, whereas the Himalayan ranges block these clouds, providing consistently clear skies. | AQ8: It helps preserve the natural navigation cues for migratory birds, which can otherwise be easily confused by bright artificial lighting. | AR8: (1, 2, [3, 4, 5]) | AS8: [1, 2, 3, 4] | AT8: (1, 2) | AU8: Error | AV8: [1, 2, 3] | AW8: 8 pattern | AX8: B) The sun obscures the summer solstice constellations during the summer, but during the winter, the night side of the Earth faces them. | AY8: B) They appear much smaller and squished together compared to the constellations near the celestial equator. | AZ8: B) Jupiter appears high in the dark night sky and is exceptionally bright, whereas Mercury is only visible very close to the horizon during sunrise or sunset and is often hidden by clouds. | BA8: C) Mars | BB8: B) Because the light of non-point objects is spread over an area, which can make them appear dimmer than their total magnitude suggests.
A9: 46179.724 | B9: gaurav.jowhry1@gmail.com | C9: 34 | D9: https://colab.research.google.com/drive/141QztwmBKFnicLDchJ4sDuRKggJdiS_T | E9: =VALUE(LEFT(C9,FIND("/",C9)-1))+IF(D9<>"",5,0) -> 39 | F9: AE-0920 | G9: Aishwary Datt jowhry | H9: a.jowhry@iitg.ac.in | I9: 9717840802 | J9: It would confirm a cyclic universe model. | K9: The cooling of the universe allowed ionized nuclei to capture electrons, neutralizing their charge and stopping them from constantly scattering photons. | L9: The separation of the strong nuclear force from the electroweak force. | N9: A: Merger of two galaxies during early galaxy formation B: Black Hole Formation | O9: It is the leftover light emitted by a hot, dense plasma that permeated the entire universe roughly 400,000 years after the Big Bang. | P9: The R-process involves rapid neutron accumulation before decay, leading to larger jumps in atomic mass compared to the slower S-process | R9: The expansion of the universe compresses visible light into invisible gamma rays. | S9: The merger releases a massive amount of neutrons, which are then captured by atomic nuclei (the 'R-process') | T9: Because stars reach temperatures that immediately destroy these specific elements | U9: No, because Only elements like carbon, oxygen, neon, silicon, iron, etc. are formed from stellar synthesis except which all other elements are not directly products of stardust. | V9: They produce radiation that strips electrons from surrounding gas, promoting further star formation through collisions. | W9: The rotation of the cloud creates a centrifugal force that counteracts gravity. | X9: Our home supercluster - Laniakea | Y9: They generated rapid sequences of stellar formation that consumed all nearby matter immediately. | Z9: B) A basin of attraction where the peculiar velocities of galaxies are directed inward toward a common gravitational focal point. | AA9: C) Cosmic voids, which are vast regions nearly empty of galaxies. | AB9: C) It does not interact via the electromagnetic force, meaning it neither emits, absorbs, nor reflects light. | AC9: B) It drives the accelerating, exponential expansion of the universe on large scales. | AD9: C) Modified Newtonian Dynamics | AE9: B) Gravitational energy released as the massive cloud of gas continuously contracts under its own weight. | AF9: B) Rapid rotation and convective currents drag the Lithium into the deep, hot interior of the star where it is destroyed by nuclear reactions. | AG9: D) The initiation of sustained hydrogen-to-helium nuclear fusion in the star's core. | AH9: C) They are formed during the cataclysmic explosions of supernovae and the violent mergers of neutron stars. | AI9: C) A black hole | AJ9: B) The creation of slightly more matter than antimatter (roughly one extra per billion), allowing the material universe to exist. | AK9: A) At your zenith (directly overhead). | AL9: C) Because the angle of the celestial pole correlates to the observer's latitude on the globe. | AM9: Long-press the constellations button in the bottom left and turn off the 'Centered Only' setting. | AN9: Tap the time in the bottom right, open the precise time controls, enter your birth date and time, and then locate the Moon. | AO9: Equinox Sunrise | AP9: The light pollution in southern India has completely blinded the telescopes, making it permanently impossible to view any stars. | AQ9: It helps preserve the natural navigation cues for migratory birds, which can otherwise be easily confused by bright artificial lighting. | AR9: (1, 2, [3, 4, 5]) | AS9: [1, 2, 3, 4] | AT9: [1, 2] | AU9: Error | AV9: [1, 2, 3] | AW9: 8 pattern | AX9: B) The sun obscures the summer solstice constellations during the summer, but during the winter, the night side of the Earth faces them. | AY9: B) They appear much smaller and squished together compared to the constellations near the celestial equator. | AZ9: B) Jupiter appears high in the dark night sky and is exceptionally bright, whereas Mercury is only visible very close to the horizon during sunrise or sunset and is often hidden by clouds. | BA9: A) Venus | BB9: B) Because the light of non-point objects is spread over an area, which can make them appear dimmer than their total magnitude suggests.
A10: 46179.737 | B10: versha2809@gmail.com | C10: 39 | E10: =VALUE(LEFT(C10,FIND("/",C10)-1))+IF(D10<>"",5,0) -> 39 | F10: AE-0525 | G10: Versha | H10: versha2809@gmail.com | I10: 9499186028 | J10: It would disprove the idea that the universe originated from a single point. | K10: The cooling of the universe allowed ionized nuclei to capture electrons, neutralizing their charge and stopping them from constantly scattering photons. | L10: The separation of the strong nuclear force from the electroweak force. | N10: A: Merger of two galaxies during early galaxy formation B: Death of a star | O10: It is the leftover light emitted by a hot, dense plasma that permeated the entire universe roughly 400,000 years after the Big Bang. | P10: The R-process involves rapid neutron accumulation before decay, leading to larger jumps in atomic mass compared to the slower S-process | R10: The universe is not infinitely old, meaning light from the most distant stars has simply not had enough time to reach us. | S10: The merger releases a massive amount of neutrons, which are then captured by atomic nuclei (the 'R-process') | T10: Because stars reach temperatures that immediately destroy these specific elements | U10: Yes, because hydrogen and helium were primarily formed during the Big Bang which later went on to become stars where other elements were created. | V10: They produce radiation that strips electrons from surrounding gas, promoting further star formation through collisions. | W10: The temperature rises until the outward kinetic energy of the gas balances the inward gravitational pull. | X10: Our home supercluster - Laniakea | Y10: Random energy spawnings caused matter to clump together, a pattern that magnified as the universe expanded. | Z10: B) A basin of attraction where the peculiar velocities of galaxies are directed inward toward a common gravitational focal point. | AA10: C) Cosmic voids, which are vast regions nearly empty of galaxies. | AB10: C) It does not interact via the electromagnetic force, meaning it neither emits, absorbs, nor reflects light. | AC10: B) It drives the accelerating, exponential expansion of the universe on large scales. | AD10: C) Modified Newtonian Dynamics | AE10: B) Gravitational energy released as the massive cloud of gas continuously contracts under its own weight. | AF10: B) Rapid rotation and convective currents drag the Lithium into the deep, hot interior of the star where it is destroyed by nuclear reactions. | AG10: D) The initiation of sustained hydrogen-to-helium nuclear fusion in the star's core. | AH10: C) They are formed during the cataclysmic explosions of supernovae and the violent mergers of neutron stars. | AI10: C) A black hole | AJ10: B) The creation of slightly more matter than antimatter (roughly one extra per billion), allowing the material universe to exist. | AK10: A) At your zenith (directly overhead). | AL10: C) Because the angle of the celestial pole correlates to the observer's latitude on the globe. | AM10: Long-press the constellations button in the bottom left and turn off the 'Centered Only' setting. | AN10: Tap the time in the bottom right, open the precise time controls, enter your birth date and time, and then locate the Moon. | AO10: Equinox Sunrise | AP10: The monsoon clouds heavily affect southern India, forcing observatories to shut down for months, whereas the Himalayan ranges block these clouds, providing consistently clear skies. | AQ10: It helps preserve the natural navigation cues for migratory birds, which can otherwise be easily confused by bright artificial lighting. | AR10: (1, 2, [3, 4, 5]) | AS10: [1, 2, 3, 4] | AT10: (1, 2) | AU10: Error | AV10: [1, 2, 3] | AW10: 8 pattern | AX10: B) The sun obscures the summer solstice constellations during the summer, but during the winter, the night side of the Earth faces them. | AY10: A) They appear significantly stretched out horizontally compared to how they actually look in the night sky. | AZ10: B) Jupiter appears high in the dark night sky and is exceptionally bright, whereas Mercury is only visible very close to the horizon during sunrise or sunset and is often hidden by clouds. | BA10: C) Mars | BB10: B) Because the light of non-point objects is spread over an area, which can make them appear dimmer than their total magnitude suggests.
A11: 46179.74 | B11: fazleabbasnajmi@gmail.com | C11: 34 | E11: =VALUE(LEFT(C11,FIND("/",C11)-1))+IF(D11<>"",5,0) -> 34 | F11: AE-0973 | G11: Fazleabbas Najmi | H11: fazleabbasnajmi@gmail.com | I11: 9106330332 | K11: The cooling of the universe allowed ionized nuclei to capture electrons, neutralizing their charge and stopping them from constantly scattering photons. | L11: The separation of the strong nuclear force from the electroweak force. | O11: It is the leftover light emitted by a hot, dense plasma that permeated the entire universe roughly 400,000 years after the Big Bang. | P11: The R-process involves rapid neutron accumulation before decay, leading to larger jumps in atomic mass compared to the slower S-process | R11: The universe is not infinitely old, meaning light from the most distant stars has simply not had enough time to reach us. | S11: The merger releases a massive amount of neutrons, which are then captured by atomic nuclei (the 'R-process') | T11: Because stars reach temperatures that immediately destroy these specific elements | U11: No, because stardust only contains heavy metals and cannot form hydrogen | V11: They produce radiation that strips electrons from surrounding gas, promoting further star formation through collisions. | W11: The temperature rises until the outward kinetic energy of the gas balances the inward gravitational pull. | Y11: Random energy spawnings caused matter to clump together, a pattern that magnified as the universe expanded. | Z11: B) A basin of attraction where the peculiar velocities of galaxies are directed inward toward a common gravitational focal point. | AA11: C) Cosmic voids, which are vast regions nearly empty of galaxies. | AB11: C) It does not interact via the electromagnetic force, meaning it neither emits, absorbs, nor reflects light. | AC11: B) It drives the accelerating, exponential expansion of the universe on large scales. | AD11: C) Modified Newtonian Dynamics | AE11: B) Gravitational energy released as the massive cloud of gas continuously contracts under its own weight. | AF11: B) Rapid rotation and convective currents drag the Lithium into the deep, hot interior of the star where it is destroyed by nuclear reactions. | AG11: D) The initiation of sustained hydrogen-to-helium nuclear fusion in the star's core. | AH11: C) They are formed during the cataclysmic explosions of supernovae and the violent mergers of neutron stars. | AI11: C) A black hole | AJ11: B) The creation of slightly more matter than antimatter (roughly one extra per billion), allowing the material universe to exist. | AK11: A) At your zenith (directly overhead). | AL11: C) Because the angle of the celestial pole correlates to the observer's latitude on the globe. | AM11: Long-press the constellations button in the bottom left and turn off the 'Centered Only' setting. | AN11: Tap the time in the bottom right, open the precise time controls, enter your birth date and time, and then locate the Moon. | AP11: The monsoon clouds heavily affect southern India, forcing observatories to shut down for months, whereas the Himalayan ranges block these clouds, providing consistently clear skies. | AQ11: It helps preserve the natural navigation cues for migratory birds, which can otherwise be easily confused by bright artificial lighting. | AS11: [1, 2, 3, 4] | AT11: (1, 2) | AU11: Error | AV11: [1, 2, 3] | AX11: B) The sun obscures the summer solstice constellations during the summer, but during the winter, the night side of the Earth faces them. | AY11: A) They appear significantly stretched out horizontally compared to how they actually look in the night sky. | AZ11: B) Jupiter appears high in the dark night sky and is exceptionally bright, whereas Mercury is only visible very close to the horizon during sunrise or sunset and is often hidden by clouds. | BA11: C) Mars | BB11: B) Because the light of non-point objects is spread over an area, which can make them appear dimmer than their total magnitude suggests.
A12: 46179.787 | B12: aayedhassan26@gmail.com | C12: 34 | D12: https://colab.research.google.com/drive/1oWKT0nsfqsdhNKEqK92_rNr7N12Sz5A4?usp=sharing | E12: =VALUE(LEFT(C12,FIND("/",C12)-1))+IF(D12<>"",5,0) -> 39 | F12: AE-0046 | G12: Aayed Hassan | H12: syed.hassan@iitg.ac.in | I12: 7070883463 | J12: It would disprove the idea that the universe originated from a single point. | K12: The cooling of the universe allowed ionized nuclei to capture electrons, neutralizing their charge and stopping them from constantly scattering photons. | L12: The separation of the strong nuclear force from the electroweak force. | N12: A: Merger of two galaxies during early galaxy formation B: Black Hole Formation | O12: It is the leftover light emitted by a hot, dense plasma that permeated the entire universe roughly 400,000 years after the Big Bang. | P12: The R-process involves rapid neutron accumulation before decay, leading to larger jumps in atomic mass compared to the slower S-process | R12: The universe is not infinitely old, meaning light from the most distant stars has simply not had enough time to reach us. | S12: The merger releases a massive amount of neutrons, which are then captured by atomic nuclei (the 'R-process') | T12: Because stellar fusion processes skip over them due to their position on the binding energy curve, making them harder to fuse | U12: Yes, because hydrogen and helium were primarily formed during the Big Bang which later went on to become stars where other elements were created. | V12: They produce radiation that strips electrons from surrounding gas, promoting further star formation through collisions. | W12: Nuclear fusion creates enough outward pressure to stop gravity. | X12: The local flow of galaxies toward the Virgo Cluster | Y12: Random energy spawnings caused matter to clump together, a pattern that magnified as the universe expanded. | Z12: B) A basin of attraction where the peculiar velocities of galaxies are directed inward toward a common gravitational focal point. | AA12: C) Cosmic voids, which are vast regions nearly empty of galaxies. | AB12: C) It does not interact via the electromagnetic force, meaning it neither emits, absorbs, nor reflects light. | AC12: B) It drives the accelerating, exponential expansion of the universe on large scales. | AD12: C) Modified Newtonian Dynamics | AE12: B) Gravitational energy released as the massive cloud of gas continuously contracts under its own weight. | AF12: B) Rapid rotation and convective currents drag the Lithium into the deep, hot interior of the star where it is destroyed by nuclear reactions. | AG12: A) The complete dissipation and outward blowing away of the surrounding protoplanetary disc. | AH12: C) They are formed during the cataclysmic explosions of supernovae and the violent mergers of neutron stars. | AI12: C) A black hole | AJ12: B) The creation of slightly more matter than antimatter (roughly one extra per billion), allowing the material universe to exist. | AK12: A) At your zenith (directly overhead). | AL12: B) Because the Earth's rotation axis is tilted relative to the ecliptic plane. | AM12: Long-press the constellations button in the bottom left and turn off the 'Centered Only' setting. | AN12: Tap the time in the bottom right, open the precise time controls, enter your birth date and time, and then locate the Moon. | AO12: Summer Solstice Sunrise | AP12: The monsoon clouds heavily affect southern India, forcing observatories to shut down for months, whereas the Himalayan ranges block these clouds, providing consistently clear skies. | AQ12: It helps preserve the natural navigation cues for migratory birds, which can otherwise be easily confused by bright artificial lighting. | AR12: (1, 2, [3, 4, 5]) | AS12: [1, 2, 3, 4] | AT12: (1, 2) | AU12: Error | AV12: [1, 2, 3, 4] | AW12: ∞ pattrn | AX12: B) The sun obscures the summer solstice constellations during the summer, but during the winter, the night side of the Earth faces them. | AY12: A) They appear significantly stretched out horizontally compared to how they actually look in the night sky. | AZ12: B) Jupiter appears high in the dark night sky and is exceptionally bright, whereas Mercury is only visible very close to the horizon during sunrise or sunset and is often hidden by clouds. | BA12: C) Mars | BB12: B) Because the light of non-point objects is spread over an area, which can make them appear dimmer than their total magnitude suggests.
A13: 46179.802 | B13: itsanoopa7@gmail.com | C13: 38 | D13: https://drive.google.com/file/d/1p45ZJYE-9bdJ9AyOEZSnNC_shLMHSpe-/view?usp=sharing | E13: =VALUE(LEFT(C13,FIND("/",C13)-1))+IF(D13<>"",5,0) -> 43 | F13: AE-0913 | G13: Anoop A | H13: itsanoopa7@gmail.com | I13: 6282704483 | J13: It would confirm a cyclic universe model. | K13: The cooling of the universe allowed ionized nuclei to capture electrons, neutralizing their charge and stopping them from constantly scattering photons. | L13: The separation of gravity from the unified forces at the end of the Planck Epoch. | N13: A: Merger of two galaxies during early galaxy formation B: Black Hole Formation | O13: It is the leftover light emitted by a hot, dense plasma that permeated the entire universe roughly 400,000 years after the Big Bang. | P13: The R-process involves rapid neutron accumulation before decay, leading to larger jumps in atomic mass compared to the slower S-process | R13: The universe is not infinitely old, meaning light from the most distant stars has simply not had enough time to reach us. | S13: The merger releases a massive amount of neutrons, which are then captured by atomic nuclei (the 'R-process') | T13: Because stellar fusion processes skip over them due to their position on the binding energy curve, making them harder to fuse | U13: No, because Only elements like carbon, oxygen, neon, silicon, iron, etc. are formed from stellar synthesis except which all other elements are not directly products of stardust. | V13: They consume all available hydrogen, preventing further galaxy formation. | W13: The temperature rises until the outward kinetic energy of the gas balances the inward gravitational pull. | X13: Our home supercluster - Laniakea | Y13: Random energy spawnings caused matter to clump together, a pattern that magnified as the universe expanded. | Z13: B) A basin of attraction where the peculiar velocities of galaxies are directed inward toward a common gravitational focal point. | AA13: C) Cosmic voids, which are vast regions nearly empty of galaxies. | AB13: C) It does not interact via the electromagnetic force, meaning it neither emits, absorbs, nor reflects light. | AC13: B) It drives the accelerating, exponential expansion of the universe on large scales. | AD13: C) Modified Newtonian Dynamics | AE13: B) Gravitational energy released as the massive cloud of gas continuously contracts under its own weight. | AF13: A) Lithium evaporates rapidly from the star's surface due to intense, outward-flowing stellar winds. | AG13: D) The initiation of sustained hydrogen-to-helium nuclear fusion in the star's core. | AH13: C) They are formed during the cataclysmic explosions of supernovae and the violent mergers of neutron stars. | AI13: C) A black hole | AJ13: B) The creation of slightly more matter than antimatter (roughly one extra per billion), allowing the material universe to exist. | AK13: A) At your zenith (directly overhead). | AL13: C) Because the angle of the celestial pole correlates to the observer's latitude on the globe. | AM13: Long-press the constellations button in the bottom left and turn off the 'Centered Only' setting. | AN13: Tap the time in the bottom right, open the precise time controls, enter your birth date and time, and then locate the Moon. | AO13: Equinox Sunrise | AP13: The monsoon clouds heavily affect southern India, forcing observatories to shut down for months, whereas the Himalayan ranges block these clouds, providing consistently clear skies. | AQ13: It helps preserve the natural navigation cues for migratory birds, which can otherwise be easily confused by bright artificial lighting. | AR13: (1, 2, [3, 4, 5]) | AS13: [1, 2, 3, 4] | AT13: (1, 2) | AU13: Error | AV13: [1, 2, 3] | AW13: 8 pattern | AX13: B) The sun obscures the summer solstice constellations during the summer, but during the winter, the night side of the Earth faces them. | AY13: A) They appear significantly stretched out horizontally compared to how they actually look in the night sky. | AZ13: B) Jupiter appears high in the dark night sky and is exceptionally bright, whereas Mercury is only visible very close to the horizon during sunrise or sunset and is often hidden by clouds. | BA13: C) Mars | BB13: B) Because the light of non-point objects is spread over an area, which can make them appear dimmer than their total magnitude suggests.
A14: 46179.807 | B14: abhinav.25.me@gmail.com | C14: 34 | D14: https://colab.research.google.com/drive/1m_u6bq7HTIN2WEzAzXvznZ1Yk34petcp?usp=sharing | E14: =VALUE(LEFT(C14,FIND("/",C14)-1))+IF(D14<>"",5,0) -> 39 | F14: AE-0128 | G14: Abhinav Srivastava | H14: Abhinavs.dd25.me@nitp.ac.in | I14: 9835327053 | J14: It would confirm a cyclic universe model. | K14: The cooling of the universe allowed ionized nuclei to capture electrons, neutralizing their charge and stopping them from constantly scattering photons. | L14: The separation of gravity from the unified forces at the end of the Planck Epoch. | N14: A: Merger of two galaxies during early galaxy formation B: Black Hole Formation | O14: It is the leftover light emitted by a hot, dense plasma that permeated the entire universe roughly 400,000 years after the Big Bang. | S14: The merger releases a massive amount of neutrons, which are then captured by atomic nuclei (the 'R-process') | T14: Because stellar fusion processes skip over them due to their position on the binding energy curve, making them harder to fuse | U14: Yes, because hydrogen and helium were primarily formed during the Big Bang which later went on to become stars where other elements were created. | V14: They reduce the temperature of the universe, allowing neutral atoms to reform. | W14: The temperature rises until the outward kinetic energy of the gas balances the inward gravitational pull. | X14: Our home supercluster - Laniakea | Y14: Random energy spawnings caused matter to clump together, a pattern that magnified as the universe expanded. | Z14: B) A basin of attraction where the peculiar velocities of galaxies are directed inward toward a common gravitational focal point. | AA14: C) Cosmic voids, which are vast regions nearly empty of galaxies. | AC14: B) It drives the accelerating, exponential expansion of the universe on large scales. | AD14: C) Modified Newtonian Dynamics | AE14: B) Gravitational energy released as the massive cloud of gas continuously contracts under its own weight. | AF14: B) Rapid rotation and convective currents drag the Lithium into the deep, hot interior of the star where it is destroyed by nuclear reactions. | AG14: D) The initiation of sustained hydrogen-to-helium nuclear fusion in the star's core. | AH14: B) They are synthesised steadily in the cores of low-mass, main-sequence stars like our Sun. | AI14: C) A black hole | AJ14: B) The creation of slightly more matter than antimatter (roughly one extra per billion), allowing the material universe to exist. | AK14: A) At your zenith (directly overhead). | AL14: C) Because the angle of the celestial pole correlates to the observer's latitude on the globe. | AM14: Long-press the constellations button in the bottom left and turn off the 'Centered Only' setting. | AN14: Tap the time in the bottom right, open the precise time controls, enter your birth date and time, and then locate the Moon. | AO14: Equinox Sunrise | AP14: The monsoon clouds heavily affect southern India, forcing observatories to shut down for months, whereas the Himalayan ranges block these clouds, providing consistently clear skies. | AQ14: It helps preserve the natural navigation cues for migratory birds, which can otherwise be easily confused by bright artificial lighting. | AR14: (1, 2, [3, 4, 5]) | AS14: [1, 2, 3, 4] | AT14: (1, 2) | AU14: Error | AV14: [1, 2, 3] | AW14: 8 pattern | AX14: B) The sun obscures the summer solstice constellations during the summer, but during the winter, the night side of the Earth faces them. | AY14: A) They appear significantly stretched out horizontally compared to how they actually look in the night sky. | AZ14: B) Jupiter appears high in the dark night sky and is exceptionally bright, whereas Mercury is only visible very close to the horizon during sunrise or sunset and is often hidden by clouds. | BA14: C) Mars | BB14: B) Because the light of non-point objects is spread over an area, which can make them appear dimmer than their total magnitude suggests.
A15: 46179.811 | B15: mannaprithwish4@gmail.com | C15: 41 | D15: https://colab.research.google.com/drive/1MNOGfOhGZZCflo5fkk1M1wvO5MBkWCa4?usp=sharing | E15: =VALUE(LEFT(C15,FIND("/",C15)-1))+IF(D15<>"",5,0) -> 46 | F15: AE-0911 | G15: Prithwish Manna | H15: m.prithwish@iitg.ac.in | I15: 9933786164 | J15: It would disprove the idea that the universe originated from a single point. | K15: The cooling of the universe allowed ionized nuclei to capture electrons, neutralizing their charge and stopping them from constantly scattering photons. | L15: The separation of the strong nuclear force from the electroweak force. | N15: A: Merger of two galaxies during early galaxy formation B: Black Hole Formation | O15: It is the leftover light emitted by a hot, dense plasma that permeated the entire universe roughly 400,000 years after the Big Bang. | P15: The R-process involves rapid neutron accumulation before decay, leading to larger jumps in atomic mass compared to the slower S-process | R15: The universe is not infinitely old, meaning light from the most distant stars has simply not had enough time to reach us. | S15: The merger releases a massive amount of neutrons, which are then captured by atomic nuclei (the 'R-process') | T15: Because stars reach temperatures that immediately destroy these specific elements | U15: No, because Only elements like carbon, oxygen, neon, silicon, iron, etc. are formed from stellar synthesis except which all other elements are not directly products of stardust. | V15: They produce radiation that strips electrons from surrounding gas, promoting further star formation through collisions. | W15: The temperature rises until the outward kinetic energy of the gas balances the inward gravitational pull. | X15: Our home supercluster - Laniakea | Y15: Random energy spawnings caused matter to clump together, a pattern that magnified as the universe expanded. | Z15: B) A basin of attraction where the peculiar velocities of galaxies are directed inward toward a common gravitational focal point. | AA15: C) Cosmic voids, which are vast regions nearly empty of galaxies. | AB15: C) It does not interact via the electromagnetic force, meaning it neither emits, absorbs, nor reflects light. | AC15: B) It drives the accelerating, exponential expansion of the universe on large scales. | AD15: C) Modified Newtonian Dynamics | AE15: B) Gravitational energy released as the massive cloud of gas continuously contracts under its own weight. | AF15: B) Rapid rotation and convective currents drag the Lithium into the deep, hot interior of the star where it is destroyed by nuclear reactions. | AG15: D) The initiation of sustained hydrogen-to-helium nuclear fusion in the star's core. | AH15: C) They are formed during the cataclysmic explosions of supernovae and the violent mergers of neutron stars. | AI15: C) A black hole | AJ15: B) The creation of slightly more matter than antimatter (roughly one extra per billion), allowing the material universe to exist. | AK15: A) At your zenith (directly overhead). | AL15: C) Because the angle of the celestial pole correlates to the observer's latitude on the globe. | AM15: Long-press the constellations button in the bottom left and turn off the 'Centered Only' setting. | AN15: Tap the time in the bottom right, open the precise time controls, enter your birth date and time, and then locate the Moon. | AO15: Equinox Sunrise | AP15: The monsoon clouds heavily affect southern India, forcing observatories to shut down for months, whereas the Himalayan ranges block these clouds, providing consistently clear skies. | AQ15: It helps preserve the natural navigation cues for migratory birds, which can otherwise be easily confused by bright artificial lighting. | AR15: (1, 2, [3, 4, 5]) | AS15: [1, 2, 3, 4] | AT15: (1, 2) | AU15: Error | AV15: [1, 2, 3] | AW15: 8 pattern | AX15: B) The sun obscures the summer solstice constellations during the summer, but during the winter, the night side of the Earth faces them. | AY15: A) They appear significantly stretched out horizontally compared to how they actually look in the night sky. | AZ15: B) Jupiter appears high in the dark night sky and is exceptionally bright, whereas Mercury is only visible very close to the horizon during sunrise or sunset and is often hidden by clouds. | BA15: C) Mars | BB15: B) Because the light of non-point objects is spread over an area, which can make them appear dimmer than their total magnitude suggests.
A16: 46179.814 | B16: mohammedarshaddevala@gmail.com | C16: 40 | E16: =VALUE(LEFT(C16,FIND("/",C16)-1))+IF(D16<>"",5,0) -> 40 | F16: AE-0995 | G16: MUHAMMED ARSHAD | H16: mohammedarshaddevala@gmail.com | I16: 6383404983 | J16: It would disprove the idea that the universe originated from a single point. | K16: The cooling of the universe allowed ionized nuclei to capture electrons, neutralizing their charge and stopping them from constantly scattering photons. | L16: The separation of the strong nuclear force from the electroweak force. | N16: A: Merger of two galaxies during early galaxy formation B: Black Hole Formation | O16: It is the leftover light emitted by a hot, dense plasma that permeated the entire universe roughly 400,000 years after the Big Bang. | P16: The R-process involves rapid neutron accumulation before decay, leading to larger jumps in atomic mass compared to the slower S-process | R16: The universe is not infinitely old, meaning light from the most distant stars has simply not had enough time to reach us. | S16: The merger releases a massive amount of neutrons, which are then captured by atomic nuclei (the 'R-process') | T16: Because stars reach temperatures that immediately destroy these specific elements | U16: No, because Only elements like carbon, oxygen, neon, silicon, iron, etc. are formed from stellar synthesis except which all other elements are not directly products of stardust. | V16: They produce radiation that strips electrons from surrounding gas, promoting further star formation through collisions. | W16: The temperature rises until the outward kinetic energy of the gas balances the inward gravitational pull. | X16: Our home supercluster - Laniakea | Y16: Random energy spawnings caused matter to clump together, a pattern that magnified as the universe expanded. | Z16: B) A basin of attraction where the peculiar velocities of galaxies are directed inward toward a common gravitational focal point. | AA16: C) Cosmic voids, which are vast regions nearly empty of galaxies. | AB16: C) It does not interact via the electromagnetic force, meaning it neither emits, absorbs, nor reflects light. | AC16: B) It drives the accelerating, exponential expansion of the universe on large scales. | AD16: C) Modified Newtonian Dynamics | AE16: B) Gravitational energy released as the massive cloud of gas continuously contracts under its own weight. | AF16: B) Rapid rotation and convective currents drag the Lithium into the deep, hot interior of the star where it is destroyed by nuclear reactions. | AG16: D) The initiation of sustained hydrogen-to-helium nuclear fusion in the star's core. | AH16: C) They are formed during the cataclysmic explosions of supernovae and the violent mergers of neutron stars. | AI16: C) A black hole | AJ16: B) The creation of slightly more matter than antimatter (roughly one extra per billion), allowing the material universe to exist. | AK16: A) At your zenith (directly overhead). | AL16: C) Because the angle of the celestial pole correlates to the observer's latitude on the globe. | AM16: Long-press the constellations button in the bottom left and turn off the 'Centered Only' setting. | AN16: Tap the time in the bottom right, open the precise time controls, enter your birth date and time, and then locate the Moon. | AO16: Summer Solstice Sunrise | AP16: The monsoon clouds heavily affect southern India, forcing observatories to shut down for months, whereas the Himalayan ranges block these clouds, providing consistently clear skies. | AQ16: It helps preserve the natural navigation cues for migratory birds, which can otherwise be easily confused by bright artificial lighting. | AR16: (1, 2, [3, 4, 5]) | AS16: [1, 2, 3, 4] | AT16: (1, 2) | AU16: Error | AV16: [1, 2, 3] | AW16: 8 pattern | AX16: B) The sun obscures the summer solstice constellations during the summer, but during the winter, the night side of the Earth faces them. | AY16: A) They appear significantly stretched out horizontally compared to how they actually look in the night sky. | AZ16: B) Jupiter appears high in the dark night sky and is exceptionally bright, whereas Mercury is only visible very close to the horizon during sunrise or sunset and is often hidden by clouds. | BA16: C) Mars | BB16: B) Because the light of non-point objects is spread over an area, which can make them appear dimmer than their total magnitude suggests.
A17: 46179.825 | B17: csn23ms173@iiserkol.ac.in | C17: 39 | D17: https://colab.research.google.com/drive/111yzithT6cQ0HUQLKb_h2UyNvwAi0__P?usp=sharing | E17: =VALUE(LEFT(C17,FIND("/",C17)-1))+IF(D17<>"",5,0) -> 44 | F17: AE-0918 | G17: Shankar Narayan | H17: csn23ms173@iiserkol.ac.in | I17: 8500795388 | J17: It would mean galaxies are not actually outside the Milky Way. | K17: The cooling of the universe allowed ionized nuclei to capture electrons, neutralizing their charge and stopping them from constantly scattering photons. | L17: The separation of the strong nuclear force from the electroweak force. | N17: A: Merger of two galaxies during early galaxy formation B: Black Hole Formation | O17: It is the leftover light emitted by a hot, dense plasma that permeated the entire universe roughly 400,000 years after the Big Bang. | P17: The R-process involves rapid neutron accumulation before decay, leading to larger jumps in atomic mass compared to the slower S-process | R17: The universe is not infinitely old, meaning light from the most distant stars has simply not had enough time to reach us. | S17: The merger releases a massive amount of neutrons, which are then captured by atomic nuclei (the 'R-process') | T17: Because stellar fusion processes skip over them due to their position on the binding energy curve, making them harder to fuse | U17: No, because Only elements like carbon, oxygen, neon, silicon, iron, etc. are formed from stellar synthesis except which all other elements are not directly products of stardust. | V17: They produce radiation that strips electrons from surrounding gas, promoting further star formation through collisions. | W17: The temperature rises until the outward kinetic energy of the gas balances the inward gravitational pull. | X17: Our home supercluster - Laniakea | Y17: Random energy spawnings caused matter to clump together, a pattern that magnified as the universe expanded. | Z17: D) The precise boundary where visible light from neighbouring superclusters is gravitationally lensed away. | AA17: C) Cosmic voids, which are vast regions nearly empty of galaxies. | AB17: C) It does not interact via the electromagnetic force, meaning it neither emits, absorbs, nor reflects light. | AC17: B) It drives the accelerating, exponential expansion of the universe on large scales. | AD17: C) Modified Newtonian Dynamics | AE17: B) Gravitational energy released as the massive cloud of gas continuously contracts under its own weight. | AF17: B) Rapid rotation and convective currents drag the Lithium into the deep, hot interior of the star where it is destroyed by nuclear reactions. | AG17: D) The initiation of sustained hydrogen-to-helium nuclear fusion in the star's core. | AH17: C) They are formed during the cataclysmic explosions of supernovae and the violent mergers of neutron stars. | AI17: C) A black hole | AJ17: B) The creation of slightly more matter than antimatter (roughly one extra per billion), allowing the material universe to exist. | AK17: A) At your zenith (directly overhead). | AL17: C) Because the angle of the celestial pole correlates to the observer's latitude on the globe. | AM17: Long-press the constellations button in the bottom left and turn off the 'Centered Only' setting. | AN17: Tap the time in the bottom right, open the precise time controls, enter your birth date and time, and then locate the Moon. | AO17: Equinox Sunrise | AP17: The monsoon clouds heavily affect southern India, forcing observatories to shut down for months, whereas the Himalayan ranges block these clouds, providing consistently clear skies. | AQ17: It helps preserve the natural navigation cues for migratory birds, which can otherwise be easily confused by bright artificial lighting. | AR17: (1, 2, [3, 4, 5]) | AS17: [1, 2, 3, 4] | AT17: (1, 2) | AU17: Error | AV17: [1, 2, 3] | AW17: ∞ pattrn | AX17: B) The sun obscures the summer solstice constellations during the summer, but during the winter, the night side of the Earth faces them. | AY17: A) They appear significantly stretched out horizontally compared to how they actually look in the night sky. | AZ17: B) Jupiter appears high in the dark night sky and is exceptionally bright, whereas Mercury is only visible very close to the horizon during sunrise or sunset and is often hidden by clouds. | BA17: C) Mars | BB17: B) Because the light of non-point objects is spread over an area, which can make them appear dimmer than their total magnitude suggests.
A18: 46179.839 | B18: dattadebarun4@gmail.com | C18: 33 | D18: https://www.kimi.com/apiv2-files/sign-obj/kimi-fs%2Fokc%2Fhwbdxbzlurng4%2F.tmp%2F20260606T143814487235Z-browser_scroll_down-tmp-23f96d7d66604366a2823ef5c2903a5c.png?filename=20260606T143814487235Z-browser_scroll_down-tmp-23f96d7d66604366a2823ef5c2903a5c.png&sig=hrndIbpJBowAKARX1XtPJTNg2hYiqorPkkW_bmisZhY=&t=o&etag=%22e063f7aa8a343e921b450b27c4886a44%22 | E18: =VALUE(LEFT(C18,FIND("/",C18)-1))+IF(D18<>"",5,0) -> 38 | F18: AE-0472 | G18: Debarun Datta | H18: dattadebarun4@gmail.com | I18: 7044483264 | J18: It would disprove the idea that the universe originated from a single point. | K18: The cooling of the universe allowed ionized nuclei to capture electrons, neutralizing their charge and stopping them from constantly scattering photons. | L18: The separation of electromagnetism from the weak nuclear force. | N18: A: A Supermassive Black Hole Merger B: Death of a star | O18: The collective thermal emission from interstellar dust and microscopic gas particles in the modern universe mimics a perfectly uniform blackbody distribution. | P18: The R-process involves rapid neutron accumulation before decay, leading to larger jumps in atomic mass compared to the slower S-process | R18: The universe is not infinitely old, meaning light from the most distant stars has simply not had enough time to reach us. | S18: The merger releases a massive amount of neutrons, which are then captured by atomic nuclei (the 'R-process') | T18: Because stellar fusion processes skip over them due to their position on the binding energy curve, making them harder to fuse | U18: Yes, because hydrogen and helium were primarily formed during the Big Bang which later went on to become stars where other elements were created. | V18: They produce radiation that strips electrons from surrounding gas, promoting further star formation through collisions. | W18: The temperature rises until the outward kinetic energy of the gas balances the inward gravitational pull. | X18: Our home supercluster - Laniakea | Y18: Random energy spawnings caused matter to clump together, a pattern that magnified as the universe expanded. | Z18: B) A basin of attraction where the peculiar velocities of galaxies are directed inward toward a common gravitational focal point. | AA18: C) Cosmic voids, which are vast regions nearly empty of galaxies. | AB18: C) It does not interact via the electromagnetic force, meaning it neither emits, absorbs, nor reflects light. | AC18: B) It drives the accelerating, exponential expansion of the universe on large scales. | AD18: A) Magnetic Oscillation and Nucleosynthesis Dynamics | AE18: B) Gravitational energy released as the massive cloud of gas continuously contracts under its own weight. | AF18: B) Rapid rotation and convective currents drag the Lithium into the deep, hot interior of the star where it is destroyed by nuclear reactions. | AG18: D) The initiation of sustained hydrogen-to-helium nuclear fusion in the star's core. | AH18: C) They are formed during the cataclysmic explosions of supernovae and the violent mergers of neutron stars. | AI18: C) A black hole | AJ18: B) The creation of slightly more matter than antimatter (roughly one extra per billion), allowing the material universe to exist. | AK18: A) At your zenith (directly overhead). | AL18: C) Because the angle of the celestial pole correlates to the observer's latitude on the globe. | AM18: Long-press the constellations button in the bottom left and turn off the 'Centered Only' setting. | AN18: Tap the time in the bottom right, open the precise time controls, enter your birth date and time, and then locate the Moon. | AO18: Equinox Sunrise | AP18: The monsoon clouds heavily affect southern India, forcing observatories to shut down for months, whereas the Himalayan ranges block these clouds, providing consistently clear skies. | AQ18: It provides a highly illuminated area that allows nocturnal animals to hunt more easily during the winter. | AR18: (1, 2, [3, 4, 5]) | AS18: [1, 2, 3] | AT18: (1, 2) | AU18: Error | AV18: [1, 2, 3, 4] | AW18: I pattern | AX18: B) The sun obscures the summer solstice constellations during the summer, but during the winter, the night side of the Earth faces them. | AY18: A) They appear significantly stretched out horizontally compared to how they actually look in the night sky. | AZ18: B) Jupiter appears high in the dark night sky and is exceptionally bright, whereas Mercury is only visible very close to the horizon during sunrise or sunset and is often hidden by clouds. | BA18: C) Mars | BB18: B) Because the light of non-point objects is spread over an area, which can make them appear dimmer than their total magnitude suggests.
A19: 46179.906 | B19: 1krishnanjansil1@gmail.com | C19: 40 | D19: https://colab.research.google.com/drive/1IEf4LhufBgrWpYU3wwdI601AtM1gyhsR?usp=sharing | E19: =VALUE(LEFT(C19,FIND("/",C19)-1))+IF(D19<>"",5,0) -> 45 | F19: AE-0388 | G19: Krishnanjan SIl | H19: 1krishnanjansil1@gmail.com | I19: 8582829570 | J19: It would disprove the idea that the universe originated from a single point. | K19: The cooling of the universe allowed ionized nuclei to capture electrons, neutralizing their charge and stopping them from constantly scattering photons. | L19: The separation of the strong nuclear force from the electroweak force. | N19: A: Merger of two galaxies during early galaxy formation B: Death of a star | O19: It is the leftover light emitted by a hot, dense plasma that permeated the entire universe roughly 400,000 years after the Big Bang. | P19: The R-process involves rapid neutron accumulation before decay, leading to larger jumps in atomic mass compared to the slower S-process | R19: The universe is not infinitely old, meaning light from the most distant stars has simply not had enough time to reach us. | S19: The merger releases a massive amount of neutrons, which are then captured by atomic nuclei (the 'R-process') | T19: Because stars reach temperatures that immediately destroy these specific elements | U19: No, because Only elements like carbon, oxygen, neon, silicon, iron, etc. are formed from stellar synthesis except which all other elements are not directly products of stardust. | V19: They produce radiation that strips electrons from surrounding gas, promoting further star formation through collisions. | W19: The temperature rises until the outward kinetic energy of the gas balances the inward gravitational pull. | X19: Our home supercluster - Laniakea | Y19: Random energy spawnings caused matter to clump together, a pattern that magnified as the universe expanded. | Z19: B) A basin of attraction where the peculiar velocities of galaxies are directed inward toward a common gravitational focal point. | AA19: C) Cosmic voids, which are vast regions nearly empty of galaxies. | AB19: C) It does not interact via the electromagnetic force, meaning it neither emits, absorbs, nor reflects light. | AC19: B) It drives the accelerating, exponential expansion of the universe on large scales. | AD19: C) Modified Newtonian Dynamics | AE19: B) Gravitational energy released as the massive cloud of gas continuously contracts under its own weight. | AF19: B) Rapid rotation and convective currents drag the Lithium into the deep, hot interior of the star where it is destroyed by nuclear reactions. | AG19: D) The initiation of sustained hydrogen-to-helium nuclear fusion in the star's core. | AH19: C) They are formed during the cataclysmic explosions of supernovae and the violent mergers of neutron stars. | AI19: C) A black hole | AJ19: B) The creation of slightly more matter than antimatter (roughly one extra per billion), allowing the material universe to exist. | AK19: A) At your zenith (directly overhead). | AL19: C) Because the angle of the celestial pole correlates to the observer's latitude on the globe. | AM19: Long-press the constellations button in the bottom left and turn off the 'Centered Only' setting. | AN19: Tap the time in the bottom right, open the precise time controls, enter your birth date and time, and then locate the Moon. | AO19: Equinox Sunrise | AP19: The monsoon clouds heavily affect southern India, forcing observatories to shut down for months, whereas the Himalayan ranges block these clouds, providing consistently clear skies. | AQ19: It helps preserve the natural navigation cues for migratory birds, which can otherwise be easily confused by bright artificial lighting. | AR19: (1, 2, [3, 4, 5]) | AS19: [1, 2, 3, 4] | AT19: (1, 2) | AU19: Error | AV19: [1, 2, 3] | AW19: 8 pattern | AX19: B) The sun obscures the summer solstice constellations during the summer, but during the winter, the night side of the Earth faces them. | AY19: A) They appear significantly stretched out horizontally compared to how they actually look in the night sky. | AZ19: B) Jupiter appears high in the dark night sky and is exceptionally bright, whereas Mercury is only visible very close to the horizon during sunrise or sunset and is often hidden by clouds. | BA19: C) Mars | BB19: B) Because the light of non-point objects is spread over an area, which can make them appear dimmer than their total magnitude suggests.
A20: 46179.907 | B20: narayanideshpande9@gmail.com | C20: 5 | D20: https://colab.research.google.com/drive/1KlWYz20vqMllfy3mR8dgklQuD5Oyul72?usp=sharing | E20: =VALUE(LEFT(C20,FIND("/",C20)-1))+IF(D20<>"",5,0) -> 10 | F20: AE-0659 | G20: Narayani Milind Deshpande | H20: narayanideshpande9@gmail.com | I20: 7821945422 | AR20: (1, 2, [3, 4, 5]) | AS20: [1, 2, 3, 4] | AT20: (1, 2) | AU20: Error | AV20: [1, 2, 3]
A21: 46179.923 | B21: saptarshid.mca24@nitp.ac.in | C21: 40 | D21: https://colab.research.google.com/drive/1GH8RaYY5sM28LlmCE-5lcwoFLL9KPntk?usp=sharing | E21: =VALUE(LEFT(C21,FIND("/",C21)-1))+IF(D21<>"",5,0) -> 45 | F21: AE 1001 | G21: Saptarshi Das | H21: saptarshid.mca24@nitp.ac.in | I21: 8637555718 | J21: It would disprove the idea that the universe originated from a single point. | K21: The cooling of the universe allowed ionized nuclei to capture electrons, neutralizing their charge and stopping them from constantly scattering photons. | L21: The separation of the strong nuclear force from the electroweak force. | N21: A: Merger of two galaxies during early galaxy formation B: Black Hole Formation | O21: It is the leftover light emitted by a hot, dense plasma that permeated the entire universe roughly 400,000 years after the Big Bang. | P21: The R-process involves rapid neutron accumulation before decay, leading to larger jumps in atomic mass compared to the slower S-process | R21: The universe is not infinitely old, meaning light from the most distant stars has simply not had enough time to reach us. | S21: The merger releases a massive amount of neutrons, which are then captured by atomic nuclei (the 'R-process') | T21: Because stellar fusion processes skip over them due to their position on the binding energy curve, making them harder to fuse | U21: Yes, because hydrogen and helium were primarily formed during the Big Bang which later went on to become stars where other elements were created. | V21: They produce radiation that strips electrons from surrounding gas, promoting further star formation through collisions. | W21: The temperature rises until the outward kinetic energy of the gas balances the inward gravitational pull. | X21: Our home supercluster - Laniakea | Y21: Random energy spawnings caused matter to clump together, a pattern that magnified as the universe expanded. | Z21: B) A basin of attraction where the peculiar velocities of galaxies are directed inward toward a common gravitational focal point. | AA21: C) Cosmic voids, which are vast regions nearly empty of galaxies. | AB21: C) It does not interact via the electromagnetic force, meaning it neither emits, absorbs, nor reflects light. | AC21: B) It drives the accelerating, exponential expansion of the universe on large scales. | AD21: C) Modified Newtonian Dynamics | AE21: B) Gravitational energy released as the massive cloud of gas continuously contracts under its own weight. | AF21: B) Rapid rotation and convective currents drag the Lithium into the deep, hot interior of the star where it is destroyed by nuclear reactions. | AG21: D) The initiation of sustained hydrogen-to-helium nuclear fusion in the star's core. | AH21: C) They are formed during the cataclysmic explosions of supernovae and the violent mergers of neutron stars. | AI21: C) A black hole | AJ21: B) The creation of slightly more matter than antimatter (roughly one extra per billion), allowing the material universe to exist. | AK21: A) At your zenith (directly overhead). | AL21: C) Because the angle of the celestial pole correlates to the observer's latitude on the globe. | AM21: Long-press the constellations button in the bottom left and turn off the 'Centered Only' setting. | AN21: Tap the time in the bottom right, open the precise time controls, enter your birth date and time, and then locate the Moon. | AO21: Equinox Sunrise | AP21: The monsoon clouds heavily affect southern India, forcing observatories to shut down for months, whereas the Himalayan ranges block these clouds, providing consistently clear skies. | AQ21: It helps preserve the natural navigation cues for migratory birds, which can otherwise be easily confused by bright artificial lighting. | AR21: (1, 2, [3, 4, 5]) | AS21: [1, 2, 3, 4] | AT21: (1, 2) | AU21: Error | AV21: [1, 2, 3] | AW21: ∞ pattrn | AX21: B) The sun obscures the summer solstice constellations during the summer, but during the winter, the night side of the Earth faces them. | AY21: A) They appear significantly stretched out horizontally compared to how they actually look in the night sky. | AZ21: B) Jupiter appears high in the dark night sky and is exceptionally bright, whereas Mercury is only visible very close to the horizon during sunrise or sunset and is often hidden by clouds. | BA21: C) Mars | BB21: B) Because the light of non-point objects is spread over an area, which can make them appear dimmer than their total magnitude suggests.
A22: 46179.977 | B22: khushi.take@gmail.com | C22: 39 | D22: https://colab.research.google.com/drive/13y6BgoKYJyQKE34hIfE0H05rL2M6mVRS?usp=sharing | E22: =VALUE(LEFT(C22,FIND("/",C22)-1))+IF(D22<>"",5,0) -> 44 | F22: AE-1112 | G22: Khushi Take | H22: khushi.take@gmail.com | I22: 7058535239 | J22: It would disprove the idea that the universe originated from a single point. | K22: The cooling of the universe allowed ionized nuclei to capture electrons, neutralizing their charge and stopping them from constantly scattering photons. | L22: The separation of the strong nuclear force from the electroweak force. | N22: A: Merger of two galaxies during early galaxy formation B: Death of a star | O22: It is the leftover light emitted by a hot, dense plasma that permeated the entire universe roughly 400,000 years after the Big Bang. | P22: The R-process involves rapid neutron accumulation before decay, leading to larger jumps in atomic mass compared to the slower S-process | R22: The universe is not infinitely old, meaning light from the most distant stars has simply not had enough time to reach us. | S22: The merger releases a massive amount of neutrons, which are then captured by atomic nuclei (the 'R-process') | T22: Because stellar fusion processes skip over them due to their position on the binding energy curve, making them harder to fuse | U22: Yes, because hydrogen and helium were primarily formed during the Big Bang which later went on to become stars where other elements were created. | V22: They produce radiation that strips electrons from surrounding gas, promoting further star formation through collisions. | W22: The temperature rises until the outward kinetic energy of the gas balances the inward gravitational pull. | X22: Our home supercluster - Laniakea | Y22: Random energy spawnings caused matter to clump together, a pattern that magnified as the universe expanded. | Z22: B) A basin of attraction where the peculiar velocities of galaxies are directed inward toward a common gravitational focal point. | AA22: C) Cosmic voids, which are vast regions nearly empty of galaxies. | AB22: C) It does not interact via the electromagnetic force, meaning it neither emits, absorbs, nor reflects light. | AC22: B) It drives the accelerating, exponential expansion of the universe on large scales. | AD22: C) Modified Newtonian Dynamics | AE22: B) Gravitational energy released as the massive cloud of gas continuously contracts under its own weight. | AF22: B) Rapid rotation and convective currents drag the Lithium into the deep, hot interior of the star where it is destroyed by nuclear reactions. | AG22: D) The initiation of sustained hydrogen-to-helium nuclear fusion in the star's core. | AH22: C) They are formed during the cataclysmic explosions of supernovae and the violent mergers of neutron stars. | AI22: C) A black hole | AJ22: B) The creation of slightly more matter than antimatter (roughly one extra per billion), allowing the material universe to exist. | AK22: A) At your zenith (directly overhead). | AL22: C) Because the angle of the celestial pole correlates to the observer's latitude on the globe. | AM22: Long-press the constellations button in the bottom left and turn off the 'Centered Only' setting. | AN22: Tap the time in the bottom right, open the precise time controls, enter your birth date and time, and then locate the Moon. | AO22: Summer Solstice Sunrise | AP22: The monsoon clouds heavily affect southern India, forcing observatories to shut down for months, whereas the Himalayan ranges block these clouds, providing consistently clear skies. | AQ22: It helps preserve the natural navigation cues for migratory birds, which can otherwise be easily confused by bright artificial lighting. | AR22: (1, 2, [3, 4, 5]) | AS22: [1, 2, 3, 4] | AT22: (1, 2) | AU22: Error | AV22: [1, 2, 3] | AW22: 8 pattern | AX22: B) The sun obscures the summer solstice constellations during the summer, but during the winter, the night side of the Earth faces them. | AY22: A) They appear significantly stretched out horizontally compared to how they actually look in the night sky. | AZ22: B) Jupiter appears high in the dark night sky and is exceptionally bright, whereas Mercury is only visible very close to the horizon during sunrise or sunset and is often hidden by clouds. | BA22: C) Mars | BB22: B) Because the light of non-point objects is spread over an area, which can make them appear dimmer than their total magnitude suggests.
A23: 46179.999 | B23: shreyas.samantray@gmail.com | C23: 36 | D23: https://colab.research.google.com/drive/1HgUpZxdVrfsOf3voy0-dht0484Fd6cpU?usp=sharing | E23: =VALUE(LEFT(C23,FIND("/",C23)-1))+IF(D23<>"",5,0) -> 41 | F23: AE-0058 | G23: Shreyas Samantray | H23: s.samantray@iitg.ac.in | I23: 7674053888 | J23: It would confirm a cyclic universe model. | K23: The cooling of the universe allowed ionized nuclei to capture electrons, neutralizing their charge and stopping them from constantly scattering photons. | L23: The separation of the strong nuclear force from the electroweak force. | N23: A: Merger of two galaxies during early galaxy formation B: Black Hole Formation | O23: It is the leftover light emitted by a hot, dense plasma that permeated the entire universe roughly 400,000 years after the Big Bang. | P23: The R-process involves rapid neutron accumulation before decay, leading to larger jumps in atomic mass compared to the slower S-process | R23: The universe is not infinitely old, meaning light from the most distant stars has simply not had enough time to reach us. | S23: The merger releases a massive amount of neutrons, which are then captured by atomic nuclei (the 'R-process') | T23: Because stars reach temperatures that immediately destroy these specific elements | U23: No, because Only elements like carbon, oxygen, neon, silicon, iron, etc. are formed from stellar synthesis except which all other elements are not directly products of stardust. | V23: They produce radiation that strips electrons from surrounding gas, promoting further star formation through collisions. | W23: The temperature rises until the outward kinetic energy of the gas balances the inward gravitational pull. | X23: Our home supercluster - Laniakea | Y23: Random energy spawnings caused matter to clump together, a pattern that magnified as the universe expanded. | Z23: B) A basin of attraction where the peculiar velocities of galaxies are directed inward toward a common gravitational focal point. | AA23: C) Cosmic voids, which are vast regions nearly empty of galaxies. | AB23: C) It does not interact via the electromagnetic force, meaning it neither emits, absorbs, nor reflects light. | AC23: B) It drives the accelerating, exponential expansion of the universe on large scales. | AD23: C) Modified Newtonian Dynamics | AE23: D) Frictional heating generated by the rapid, chaotic orbit of surrounding protoplanets. | AF23: B) Rapid rotation and convective currents drag the Lithium into the deep, hot interior of the star where it is destroyed by nuclear reactions. | AG23: D) The initiation of sustained hydrogen-to-helium nuclear fusion in the star's core. | AH23: C) They are formed during the cataclysmic explosions of supernovae and the violent mergers of neutron stars. | AI23: C) A black hole | AJ23: B) The creation of slightly more matter than antimatter (roughly one extra per billion), allowing the material universe to exist. | AK23: A) At your zenith (directly overhead). | AL23: C) Because the angle of the celestial pole correlates to the observer's latitude on the globe. | AM23: Long-press the constellations button in the bottom left and turn off the 'Centered Only' setting. | AN23: Tap the time in the bottom right, open the precise time controls, enter your birth date and time, and then locate the Moon. | AO23: Equinox Sunrise | AP23: The monsoon clouds heavily affect southern India, forcing observatories to shut down for months, whereas the Himalayan ranges block these clouds, providing consistently clear skies. | AQ23: It helps preserve the natural navigation cues for migratory birds, which can otherwise be easily confused by bright artificial lighting. | AR23: (1, 2, [3, 4, 5]) | AS23: [1, 2, 3] | AT23: (1, 2) | AU23: Error | AV23: [1, 2, 3] | AW23: 8 pattern | AX23: B) The sun obscures the summer solstice constellations during the summer, but during the winter, the night side of the Earth faces them. | AY23: A) They appear significantly stretched out horizontally compared to how they actually look in the night sky. | AZ23: B) Jupiter appears high in the dark night sky and is exceptionally bright, whereas Mercury is only visible very close to the horizon during sunrise or sunset and is often hidden by clouds. | BA23: D) Jupiter
A24: 46180.387 | B24: akash04.vars@gmail.com | C24: 40 | D24: https://colab.research.google.com/drive/1gTT5JFZO8EiZlb3K1IQw9D0JgftUgzE3?usp=sharing | E24: =VALUE(LEFT(C24,FIND("/",C24)-1))+IF(D24<>"",5,0) -> 45 | F24: AE-0698 | G24: AKASH SANKAR VIGNESHWARAN | H24: akash04.vars@gmail.com | I24: 9080227279 | J24: It would disprove the idea that the universe originated from a single point. | K24: The cooling of the universe allowed ionized nuclei to capture electrons, neutralizing their charge and stopping them from constantly scattering photons. | L24: The separation of the strong nuclear force from the electroweak force. | N24: A: Merger of two galaxies during early galaxy formation B: Black Hole Formation | O24: It is the leftover light emitted by a hot, dense plasma that permeated the entire universe roughly 400,000 years after the Big Bang. | P24: The R-process involves rapid neutron accumulation before decay, leading to larger jumps in atomic mass compared to the slower S-process | R24: The universe is not infinitely old, meaning light from the most distant stars has simply not had enough time to reach us. | S24: The merger releases a massive amount of neutrons, which are then captured by atomic nuclei (the 'R-process') | T24: Because stars reach temperatures that immediately destroy these specific elements | U24: Yes, because hydrogen and helium were primarily formed during the Big Bang which later went on to become stars where other elements were created. | V24: They produce radiation that strips electrons from surrounding gas, promoting further star formation through collisions. | W24: The temperature rises until the outward kinetic energy of the gas balances the inward gravitational pull. | X24: Our home supercluster - Laniakea | Y24: Random energy spawnings caused matter to clump together, a pattern that magnified as the universe expanded. | Z24: B) A basin of attraction where the peculiar velocities of galaxies are directed inward toward a common gravitational focal point. | AA24: C) Cosmic voids, which are vast regions nearly empty of galaxies. | AB24: C) It does not interact via the electromagnetic force, meaning it neither emits, absorbs, nor reflects light. | AC24: B) It drives the accelerating, exponential expansion of the universe on large scales. | AD24: C) Modified Newtonian Dynamics | AE24: B) Gravitational energy released as the massive cloud of gas continuously contracts under its own weight. | AF24: B) Rapid rotation and convective currents drag the Lithium into the deep, hot interior of the star where it is destroyed by nuclear reactions. | AG24: D) The initiation of sustained hydrogen-to-helium nuclear fusion in the star's core. | AH24: C) They are formed during the cataclysmic explosions of supernovae and the violent mergers of neutron stars. | AI24: C) A black hole | AJ24: B) The creation of slightly more matter than antimatter (roughly one extra per billion), allowing the material universe to exist. | AK24: A) At your zenith (directly overhead). | AL24: C) Because the angle of the celestial pole correlates to the observer's latitude on the globe. | AM24: Long-press the constellations button in the bottom left and turn off the 'Centered Only' setting. | AN24: Tap the time in the bottom right, open the precise time controls, enter your birth date and time, and then locate the Moon. | AO24: Equinox Sunrise | AP24: The monsoon clouds heavily affect southern India, forcing observatories to shut down for months, whereas the Himalayan ranges block these clouds, providing consistently clear skies. | AQ24: It helps preserve the natural navigation cues for migratory birds, which can otherwise be easily confused by bright artificial lighting. | AR24: (1, 2, [3, 4, 5]) | AS24: [1, 2, 3, 4] | AT24: (1, 2) | AU24: Error | AV24: [1, 2, 3] | AW24: 8 pattern | AX24: B) The sun obscures the summer solstice constellations during the summer, but during the winter, the night side of the Earth faces them. | AY24: A) They appear significantly stretched out horizontally compared to how they actually look in the night sky. | AZ24: B) Jupiter appears high in the dark night sky and is exceptionally bright, whereas Mercury is only visible very close to the horizon during sunrise or sunset and is often hidden by clouds. | BA24: C) Mars | BB24: B) Because the light of non-point objects is spread over an area, which can make them appear dimmer than their total magnitude suggests.
A25: 46180.397 | B25: ghoshsrijayan66@gmail.com | C25: 14 | E25: =VALUE(LEFT(C25,FIND("/",C25)-1))+IF(D25<>"",5,0) -> 14 | F25: AE-0722 | G25: Srijayan Ghosh | H25: ghoshsrijayan66@gmail.com | I25: 8158944826 | J25: It would disprove the idea that the universe originated from a single point. | K25: The cooling of the universe allowed ionized nuclei to capture electrons, neutralizing their charge and stopping them from constantly scattering photons. | L25: The separation of the strong nuclear force from the electroweak force. | N25: A: Merger of two galaxies during early galaxy formation B: Death of a star | O25: The collective thermal emission from interstellar dust and microscopic gas particles in the modern universe mimics a perfectly uniform blackbody distribution. | P25: The R-process only creates stable elements, while the S-process only creates radioactive isotopes | R25: The expansion of the universe compresses visible light into invisible gamma rays. | S25: The merger releases a massive amount of neutrons, which are then captured by atomic nuclei (the 'R-process') | T25: Because stars reach temperatures that immediately destroy these specific elements | U25: Yes, because hydrogen and helium were primarily formed during the Big Bang which later went on to become stars where other elements were created. | V25: They produce radiation that strips electrons from surrounding gas, promoting further star formation through collisions. | W25: The temperature rises until the outward kinetic energy of the gas balances the inward gravitational pull. | X25: Our home supercluster - Laniakea | Y25: Random energy spawnings caused matter to clump together, a pattern that magnified as the universe expanded. | Z25: B) A basin of attraction where the peculiar velocities of galaxies are directed inward toward a common gravitational focal point. | AA25: C) Cosmic voids, which are vast regions nearly empty of galaxies. | AB25: C) It does not interact via the electromagnetic force, meaning it neither emits, absorbs, nor reflects light. | AC25: A) It binds the outer edges of rotating galaxies together, preventing them from flying apart due to centrifugal forces. | AD25: C) Modified Newtonian Dynamics | AE25: B) Gravitational energy released as the massive cloud of gas continuously contracts under its own weight. | AF25: D) The Lithium undergoes spontaneous radioactive decay into Helium over a period of ten million years. | AG25: D) The initiation of sustained hydrogen-to-helium nuclear fusion in the star's core. | AH25: B) They are synthesised steadily in the cores of low-mass, main-sequence stars like our Sun. | AI25: C) A black hole | AJ25: D) The concentration of all primordial matter into a single, massive supercluster.
A26: 46180.447 | B26: debojeetchowdhury59@gmail.com | C26: 32 | E26: =VALUE(LEFT(C26,FIND("/",C26)-1))+IF(D26<>"",5,0) -> 32 | F26: AE1020 | G26: Debojeet Chowdhury | H26: debojeetchowdhury59@gmail.com | I26: 7099015663 | J26: It would disprove the idea that the universe originated from a single point. | K26: The cooling of the universe allowed ionized nuclei to capture electrons, neutralizing their charge and stopping them from constantly scattering photons. | L26: The separation of the strong nuclear force from the electroweak force. | O26: The continuous annihilation of virtual particle-antiparticle pairs in the quantum vacuum generates a uniform thermal radiation profile. | P26: The R-process involves rapid neutron accumulation before decay, leading to larger jumps in atomic mass compared to the slower S-process | R26: The universe is not infinitely old, meaning light from the most distant stars has simply not had enough time to reach us. | S26: The merger releases a massive amount of neutrons, which are then captured by atomic nuclei (the 'R-process') | T26: Because stars reach temperatures that immediately destroy these specific elements | U26: No, because stardust only contains heavy metals and cannot form hydrogen | V26: They reduce the temperature of the universe, allowing neutral atoms to reform. | W26: The temperature rises until the outward kinetic energy of the gas balances the inward gravitational pull. | X26: Our home supercluster - Laniakea | Y26: Random energy spawnings caused matter to clump together, a pattern that magnified as the universe expanded. | Z26: B) A basin of attraction where the peculiar velocities of galaxies are directed inward toward a common gravitational focal point. | AA26: C) Cosmic voids, which are vast regions nearly empty of galaxies. | AB26: C) It does not interact via the electromagnetic force, meaning it neither emits, absorbs, nor reflects light. | AC26: B) It drives the accelerating, exponential expansion of the universe on large scales. | AD26: C) Modified Newtonian Dynamics | AE26: B) Gravitational energy released as the massive cloud of gas continuously contracts under its own weight. | AF26: B) Rapid rotation and convective currents drag the Lithium into the deep, hot interior of the star where it is destroyed by nuclear reactions. | AG26: D) The initiation of sustained hydrogen-to-helium nuclear fusion in the star's core. | AH26: C) They are formed during the cataclysmic explosions of supernovae and the violent mergers of neutron stars. | AI26: C) A black hole | AJ26: B) The creation of slightly more matter than antimatter (roughly one extra per billion), allowing the material universe to exist. | AK26: A) At your zenith (directly overhead). | AL26: C) Because the angle of the celestial pole correlates to the observer's latitude on the globe. | AM26: Long-press the constellations button in the bottom left and turn off the 'Centered Only' setting. | AN26: Tap the time in the bottom right, open the precise time controls, enter your birth date and time, and then locate the Moon. | AO26: Winter Solstice Sunrise | AP26: The monsoon clouds heavily affect southern India, forcing observatories to shut down for months, whereas the Himalayan ranges block these clouds, providing consistently clear skies. | AQ26: It helps preserve the natural navigation cues for migratory birds, which can otherwise be easily confused by bright artificial lighting. | AR26: (1, 2, [3, 4, 5]) | AS26: [1, 2, 3, 4] | AT26: {1, 2} | AU26: 2 | AV26: Error | AW26: ∞ pattrn | AX26: B) The sun obscures the summer solstice constellations during the summer, but during the winter, the night side of the Earth faces them. | AY26: A) They appear significantly stretched out horizontally compared to how they actually look in the night sky. | AZ26: B) Jupiter appears high in the dark night sky and is exceptionally bright, whereas Mercury is only visible very close to the horizon during sunrise or sunset and is often hidden by clouds. | BA26: C) Mars | BB26: B) Because the light of non-point objects is spread over an area, which can make them appear dimmer than their total magnitude suggests.
A27: 46180.465 | B27: dnagasathvik@gmail.com | C27: 38 | D27: https://colab.research.google.com/drive/1IaJAJc2PzOMBwH7c8N_hu8tK-izZqNhO?usp=sharing | E27: =VALUE(LEFT(C27,FIND("/",C27)-1))+IF(D27<>"",5,0) -> 43 | F27: AE-0819 | G27: D. Naga Sathvik | H27: dnagasathvik@gmail.com | I27: 7675975489 | J27: It would disprove the idea that the universe originated from a single point. | K27: The cooling of the universe allowed ionized nuclei to capture electrons, neutralizing their charge and stopping them from constantly scattering photons. | L27: The separation of the strong nuclear force from the electroweak force. | N27: A: A Supermassive Black Hole Merger B: Black Hole Formation | O27: It is the leftover light emitted by a hot, dense plasma that permeated the entire universe roughly 400,000 years after the Big Bang. | P27: The R-process involves rapid neutron accumulation before decay, leading to larger jumps in atomic mass compared to the slower S-process | R27: The universe is not infinitely old, meaning light from the most distant stars has simply not had enough time to reach us. | S27: The merger releases a massive amount of neutrons, which are then captured by atomic nuclei (the 'R-process') | T27: Because stellar fusion processes skip over them due to their position on the binding energy curve, making them harder to fuse | U27: Yes, because hydrogen and helium were primarily formed during the Big Bang which later went on to become stars where other elements were created. | V27: They produce radiation that strips electrons from surrounding gas, promoting further star formation through collisions. | W27: The temperature rises until the outward kinetic energy of the gas balances the inward gravitational pull. | X27: Our home supercluster - Laniakea | Y27: Random energy spawnings caused matter to clump together, a pattern that magnified as the universe expanded. | Z27: B) A basin of attraction where the peculiar velocities of galaxies are directed inward toward a common gravitational focal point. | AA27: C) Cosmic voids, which are vast regions nearly empty of galaxies. | AB27: C) It does not interact via the electromagnetic force, meaning it neither emits, absorbs, nor reflects light. | AC27: B) It drives the accelerating, exponential expansion of the universe on large scales. | AD27: C) Modified Newtonian Dynamics | AE27: B) Gravitational energy released as the massive cloud of gas continuously contracts under its own weight. | AF27: B) Rapid rotation and convective currents drag the Lithium into the deep, hot interior of the star where it is destroyed by nuclear reactions. | AG27: D) The initiation of sustained hydrogen-to-helium nuclear fusion in the star's core. | AH27: C) They are formed during the cataclysmic explosions of supernovae and the violent mergers of neutron stars. | AI27: C) A black hole | AJ27: B) The creation of slightly more matter than antimatter (roughly one extra per billion), allowing the material universe to exist. | AK27: A) At your zenith (directly overhead). | AL27: C) Because the angle of the celestial pole correlates to the observer's latitude on the globe. | AM27: Long-press the constellations button in the bottom left and turn off the 'Centered Only' setting. | AN27: Tap the time in the bottom right, open the precise time controls, enter your birth date and time, and then locate the Moon. | AO27: Equinox Sunrise | AP27: The monsoon clouds heavily affect southern India, forcing observatories to shut down for months, whereas the Himalayan ranges block these clouds, providing consistently clear skies. | AQ27: It helps preserve the natural navigation cues for migratory birds, which can otherwise be easily confused by bright artificial lighting. | AR27: (1, 2, [3, 4, 5]) | AS27: [1, 2, 3, 4] | AT27: (1, 2) | AU27: Error | AV27: [1, 2, 3] | AW27: ∞ pattrn | AX27: B) The sun obscures the summer solstice constellations during the summer, but during the winter, the night side of the Earth faces them. | AY27: B) They appear much smaller and squished together compared to the constellations near the celestial equator. | AZ27: B) Jupiter appears high in the dark night sky and is exceptionally bright, whereas Mercury is only visible very close to the horizon during sunrise or sunset and is often hidden by clouds. | BA27: C) Mars | BB27: B) Because the light of non-point objects is spread over an area, which can make them appear dimmer than their total magnitude suggests.
A28: 46180.502 | B28: ranitsen7264@gmail.com | C28: 39 | D28: https://colab.research.google.com/drive/1W35vMX2qWz1nptDeHw_opn3bNjm6AH_M?usp=sharing | E28: =VALUE(LEFT(C28,FIND("/",C28)-1))+IF(D28<>"",5,0) -> 44 | F28: AE-0512 | G28: Ranit Sen | H28: ranitsen7264@gmail.com | I28: 6289954702 | J28: It would disprove the idea that the universe originated from a single point. | K28: The cooling of the universe allowed ionized nuclei to capture electrons, neutralizing their charge and stopping them from constantly scattering photons. | L28: The separation of gravity from the unified forces at the end of the Planck Epoch. | N28: A: A Supermassive Black Hole Merger B: Black Hole Formation | O28: It is the leftover light emitted by a hot, dense plasma that permeated the entire universe roughly 400,000 years after the Big Bang. | P28: The R-process involves rapid neutron accumulation before decay, leading to larger jumps in atomic mass compared to the slower S-process | R28: The universe is not infinitely old, meaning light from the most distant stars has simply not had enough time to reach us. | S28: The merger releases a massive amount of neutrons, which are then captured by atomic nuclei (the 'R-process') | T28: Because stellar fusion processes skip over them due to their position on the binding energy curve, making them harder to fuse | U28: Yes, because hydrogen and helium were primarily formed during the Big Bang which later went on to become stars where other elements were created. | V28: They produce radiation that strips electrons from surrounding gas, promoting further star formation through collisions. | W28: The temperature rises until the outward kinetic energy of the gas balances the inward gravitational pull. | X28: Our home supercluster - Laniakea | Y28: Random energy spawnings caused matter to clump together, a pattern that magnified as the universe expanded. | Z28: B) A basin of attraction where the peculiar velocities of galaxies are directed inward toward a common gravitational focal point. | AA28: C) Cosmic voids, which are vast regions nearly empty of galaxies. | AB28: C) It does not interact via the electromagnetic force, meaning it neither emits, absorbs, nor reflects light. | AC28: B) It drives the accelerating, exponential expansion of the universe on large scales. | AD28: C) Modified Newtonian Dynamics | AE28: B) Gravitational energy released as the massive cloud of gas continuously contracts under its own weight. | AF28: B) Rapid rotation and convective currents drag the Lithium into the deep, hot interior of the star where it is destroyed by nuclear reactions. | AG28: D) The initiation of sustained hydrogen-to-helium nuclear fusion in the star's core. | AH28: C) They are formed during the cataclysmic explosions of supernovae and the violent mergers of neutron stars. | AI28: C) A black hole | AJ28: B) The creation of slightly more matter than antimatter (roughly one extra per billion), allowing the material universe to exist. | AK28: A) At your zenith (directly overhead). | AL28: C) Because the angle of the celestial pole correlates to the observer's latitude on the globe. | AM28: Long-press the constellations button in the bottom left and turn off the 'Centered Only' setting. | AN28: Tap the time in the bottom right, open the precise time controls, enter your birth date and time, and then locate the Moon. | AO28: Equinox Sunrise | AP28: The monsoon clouds heavily affect southern India, forcing observatories to shut down for months, whereas the Himalayan ranges block these clouds, providing consistently clear skies. | AQ28: It helps preserve the natural navigation cues for migratory birds, which can otherwise be easily confused by bright artificial lighting. | AR28: (1, 2, [3, 4, 5]) | AS28: [1, 2, 3, 4] | AT28: (1, 2) | AU28: Error | AV28: [1, 2, 3] | AW28: 8 pattern | AX28: B) The sun obscures the summer solstice constellations during the summer, but during the winter, the night side of the Earth faces them. | AY28: A) They appear significantly stretched out horizontally compared to how they actually look in the night sky. | AZ28: B) Jupiter appears high in the dark night sky and is exceptionally bright, whereas Mercury is only visible very close to the horizon during sunrise or sunset and is often hidden by clouds. | BA28: C) Mars | BB28: B) Because the light of non-point objects is spread over an area, which can make them appear dimmer than their total magnitude suggests.
A29: 46180.522 | B29: rishabhyadav.dev@gmail.com | C29: 40 | D29: https://colab.research.google.com/drive/1x-hIUmu4BG6_lc9YMxOXvTaLK4-7GNi8?usp=sharing | E29: =VALUE(LEFT(C29,FIND("/",C29)-1))+IF(D29<>"",5,0) -> 45 | F29: AE-0232 | G29: Rishabh Yadav | H29: rishabhyadav.dev@gmail.com | I29: 9919937221 | J29: It would disprove the idea that the universe originated from a single point. | K29: The cooling of the universe allowed ionized nuclei to capture electrons, neutralizing their charge and stopping them from constantly scattering photons. | L29: The separation of the strong nuclear force from the electroweak force. | N29: A: Merger of two galaxies during early galaxy formation B: Black Hole Formation | O29: It is the leftover light emitted by a hot, dense plasma that permeated the entire universe roughly 400,000 years after the Big Bang. | P29: The R-process involves rapid neutron accumulation before decay, leading to larger jumps in atomic mass compared to the slower S-process | R29: The universe is not infinitely old, meaning light from the most distant stars has simply not had enough time to reach us. | S29: The merger releases a massive amount of neutrons, which are then captured by atomic nuclei (the 'R-process') | T29: Because stellar fusion processes skip over them due to their position on the binding energy curve, making them harder to fuse | U29: Yes, because hydrogen and helium were primarily formed during the Big Bang which later went on to become stars where other elements were created. | V29: They produce radiation that strips electrons from surrounding gas, promoting further star formation through collisions. | W29: The temperature rises until the outward kinetic energy of the gas balances the inward gravitational pull. | X29: Our home supercluster - Laniakea | Y29: Random energy spawnings caused matter to clump together, a pattern that magnified as the universe expanded. | Z29: B) A basin of attraction where the peculiar velocities of galaxies are directed inward toward a common gravitational focal point. | AA29: C) Cosmic voids, which are vast regions nearly empty of galaxies. | AB29: C) It does not interact via the electromagnetic force, meaning it neither emits, absorbs, nor reflects light. | AC29: B) It drives the accelerating, exponential expansion of the universe on large scales. | AD29: C) Modified Newtonian Dynamics | AE29: B) Gravitational energy released as the massive cloud of gas continuously contracts under its own weight. | AF29: B) Rapid rotation and convective currents drag the Lithium into the deep, hot interior of the star where it is destroyed by nuclear reactions. | AG29: D) The initiation of sustained hydrogen-to-helium nuclear fusion in the star's core. | AH29: C) They are formed during the cataclysmic explosions of supernovae and the violent mergers of neutron stars. | AI29: C) A black hole | AJ29: B) The creation of slightly more matter than antimatter (roughly one extra per billion), allowing the material universe to exist. | AK29: A) At your zenith (directly overhead). | AL29: C) Because the angle of the celestial pole correlates to the observer's latitude on the globe. | AM29: Long-press the constellations button in the bottom left and turn off the 'Centered Only' setting. | AN29: Tap the time in the bottom right, open the precise time controls, enter your birth date and time, and then locate the Moon. | AO29: Equinox Sunrise | AP29: The monsoon clouds heavily affect southern India, forcing observatories to shut down for months, whereas the Himalayan ranges block these clouds, providing consistently clear skies. | AQ29: It helps preserve the natural navigation cues for migratory birds, which can otherwise be easily confused by bright artificial lighting. | AR29: (1, 2, [3, 4, 5]) | AS29: [1, 2, 3, 4] | AT29: (1, 2) | AU29: Error | AV29: [1, 2, 3] | AW29: ∞ pattrn | AX29: B) The sun obscures the summer solstice constellations during the summer, but during the winter, the night side of the Earth faces them. | AY29: A) They appear significantly stretched out horizontally compared to how they actually look in the night sky. | AZ29: B) Jupiter appears high in the dark night sky and is exceptionally bright, whereas Mercury is only visible very close to the horizon during sunrise or sunset and is often hidden by clouds. | BA29: C) Mars | BB29: B) Because the light of non-point objects is spread over an area, which can make them appear dimmer than their total magnitude suggests.
A30: 46180.527 | B30: rdxrudransh124@gmail.com | C30: 37 | E30: =VALUE(LEFT(C30,FIND("/",C30)-1))+IF(D30<>"",5,0) -> 37 | F30: AE-0199 | G30: Rudransh | H30: rdxrudransh124@gmail.com | I30: 7988255239 | J30: It would disprove the idea that the universe originated from a single point. | K30: The cooling of the universe allowed ionized nuclei to capture electrons, neutralizing their charge and stopping them from constantly scattering photons. | L30: The separation of the strong nuclear force from the electroweak force. | N30: A: Merger of two galaxies during early galaxy formation B: Black Hole Formation | O30: It is the leftover light emitted by a hot, dense plasma that permeated the entire universe roughly 400,000 years after the Big Bang. | P30: The R-process involves rapid neutron accumulation before decay, leading to larger jumps in atomic mass compared to the slower S-process | R30: The universe is not infinitely old, meaning light from the most distant stars has simply not had enough time to reach us. | S30: The merger releases a massive amount of neutrons, which are then captured by atomic nuclei (the 'R-process') | T30: Because stellar fusion processes skip over them due to their position on the binding energy curve, making them harder to fuse | U30: Yes, because hydrogen and helium were primarily formed during the Big Bang which later went on to become stars where other elements were created. | V30: They produce radiation that strips electrons from surrounding gas, promoting further star formation through collisions. | W30: Nuclear fusion creates enough outward pressure to stop gravity. | X30: Our home supercluster - Laniakea | Y30: They generated rapid sequences of stellar formation that consumed all nearby matter immediately. | Z30: B) A basin of attraction where the peculiar velocities of galaxies are directed inward toward a common gravitational focal point. | AA30: C) Cosmic voids, which are vast regions nearly empty of galaxies. | AB30: C) It does not interact via the electromagnetic force, meaning it neither emits, absorbs, nor reflects light. | AC30: B) It drives the accelerating, exponential expansion of the universe on large scales. | AD30: C) Modified Newtonian Dynamics | AE30: B) Gravitational energy released as the massive cloud of gas continuously contracts under its own weight. | AF30: B) Rapid rotation and convective currents drag the Lithium into the deep, hot interior of the star where it is destroyed by nuclear reactions. | AG30: D) The initiation of sustained hydrogen-to-helium nuclear fusion in the star's core. | AH30: C) They are formed during the cataclysmic explosions of supernovae and the violent mergers of neutron stars. | AI30: C) A black hole | AJ30: B) The creation of slightly more matter than antimatter (roughly one extra per billion), allowing the material universe to exist. | AK30: A) At your zenith (directly overhead). | AL30: C) Because the angle of the celestial pole correlates to the observer's latitude on the globe. | AM30: Long-press the constellations button in the bottom left and turn off the 'Centered Only' setting. | AN30: Tap the time in the bottom right, open the precise time controls, enter your birth date and time, and then locate the Moon. | AO30: Equinox Sunrise | AP30: The monsoon clouds heavily affect southern India, forcing observatories to shut down for months, whereas the Himalayan ranges block these clouds, providing consistently clear skies. | AQ30: It helps preserve the natural navigation cues for migratory birds, which can otherwise be easily confused by bright artificial lighting. | AR30: (1, 2, [3, 4, 5]) | AS30: [1, 2, 3, 4] | AT30: {"a": 1} | AU30: None | AV30: [1, 2, 3] | AW30: I pattern | AX30: B) The sun obscures the summer solstice constellations during the summer, but during the winter, the night side of the Earth faces them. | AY30: A) They appear significantly stretched out horizontally compared to how they actually look in the night sky. | AZ30: B) Jupiter appears high in the dark night sky and is exceptionally bright, whereas Mercury is only visible very close to the horizon during sunrise or sunset and is often hidden by clouds. | BA30: C) Mars | BB30: B) Because the light of non-point objects is spread over an area, which can make them appear dimmer than their total magnitude suggests.
A31: 46180.538 | B31: soham.majhi2007@gmail.com | C31: 38 | D31: https://colab.research.google.com/drive/1ua-ROAonPbvim3u6ybBllPlJJbIWyQw5?usp=sharing | E31: =VALUE(LEFT(C31,FIND("/",C31)-1))+IF(D31<>"",5,0) -> 43 | F31: AE-0622 | G31: Soham Majhi | H31: soham.majhi2007@gmail.com | I31: 8910799562 | J31: It would disprove the idea that the universe originated from a single point. | K31: The cooling of the universe allowed ionized nuclei to capture electrons, neutralizing their charge and stopping them from constantly scattering photons. | L31: The separation of the strong nuclear force from the electroweak force. | N31: A: Merger of two galaxies during early galaxy formation B: Black Hole Formation | O31: It is the leftover light emitted by a hot, dense plasma that permeated the entire universe roughly 400,000 years after the Big Bang. | P31: The R-process involves rapid neutron accumulation before decay, leading to larger jumps in atomic mass compared to the slower S-process | R31: The universe is not infinitely old, meaning light from the most distant stars has simply not had enough time to reach us. | S31: The merger releases a massive amount of neutrons, which are then captured by atomic nuclei (the 'R-process') | T31: Because stars reach temperatures that immediately destroy these specific elements | U31: Yes, because hydrogen and helium were primarily formed during the Big Bang which later went on to become stars where other elements were created. | V31: They produce radiation that strips electrons from surrounding gas, promoting further star formation through collisions. | W31: The temperature rises until the outward kinetic energy of the gas balances the inward gravitational pull. | X31: Our home supercluster - Laniakea | Y31: Random energy spawnings caused matter to clump together, a pattern that magnified as the universe expanded. | Z31: B) A basin of attraction where the peculiar velocities of galaxies are directed inward toward a common gravitational focal point. | AA31: C) Cosmic voids, which are vast regions nearly empty of galaxies. | AB31: C) It does not interact via the electromagnetic force, meaning it neither emits, absorbs, nor reflects light. | AC31: B) It drives the accelerating, exponential expansion of the universe on large scales. | AD31: C) Modified Newtonian Dynamics | AE31: B) Gravitational energy released as the massive cloud of gas continuously contracts under its own weight. | AF31: B) Rapid rotation and convective currents drag the Lithium into the deep, hot interior of the star where it is destroyed by nuclear reactions. | AG31: D) The initiation of sustained hydrogen-to-helium nuclear fusion in the star's core. | AH31: C) They are formed during the cataclysmic explosions of supernovae and the violent mergers of neutron stars. | AI31: C) A black hole | AJ31: B) The creation of slightly more matter than antimatter (roughly one extra per billion), allowing the material universe to exist. | AK31: A) At your zenith (directly overhead). | AL31: C) Because the angle of the celestial pole correlates to the observer's latitude on the globe. | AM31: Long-press the constellations button in the bottom left and turn off the 'Centered Only' setting. | AN31: Tap the time in the bottom right, open the precise time controls, enter your birth date and time, and then locate the Moon. | AO31: Equinox Sunrise | AP31: The monsoon clouds heavily affect southern India, forcing observatories to shut down for months, whereas the Himalayan ranges block these clouds, providing consistently clear skies. | AQ31: It helps preserve the natural navigation cues for migratory birds, which can otherwise be easily confused by bright artificial lighting. | AR31: (1, 2, [3, 4, 5]) | AS31: [1, 2, 3, 4] | AT31: (1, 2) | AU31: None | AV31: [1, 2, 3] | AW31: ∞ pattrn | AX31: B) The sun obscures the summer solstice constellations during the summer, but during the winter, the night side of the Earth faces them. | AY31: A) They appear significantly stretched out horizontally compared to how they actually look in the night sky. | AZ31: B) Jupiter appears high in the dark night sky and is exceptionally bright, whereas Mercury is only visible very close to the horizon during sunrise or sunset and is often hidden by clouds. | BA31: C) Mars | BB31: B) Because the light of non-point objects is spread over an area, which can make them appear dimmer than their total magnitude suggests.
A32: 46180.568 | B32: deanjaat2007@gmail.com | C32: 38 | D32: https://colab.research.google.com/drive/1onkmbZTmzKwaUrFkDFExdFdlo0az13F6?usp=sharing | E32: =VALUE(LEFT(C32,FIND("/",C32)-1))+IF(D32<>"",5,0) -> 43 | F32: AE-0033 | G32: Nitin Kinha | H32: n.kinha@iitg.ac.in | I32: 9664368547 | J32: It would disprove the idea that the universe originated from a single point. | K32: The cooling of the universe allowed ionized nuclei to capture electrons, neutralizing their charge and stopping them from constantly scattering photons. | L32: The separation of the strong nuclear force from the electroweak force. | N32: A: Merger of two galaxies during early galaxy formation B: Black Hole Formation | O32: It is the leftover light emitted by a hot, dense plasma that permeated the entire universe roughly 400,000 years after the Big Bang. | P32: The R-process involves rapid neutron accumulation before decay, leading to larger jumps in atomic mass compared to the slower S-process | R32: The universe is not infinitely old, meaning light from the most distant stars has simply not had enough time to reach us. | S32: The merger releases a massive amount of neutrons, which are then captured by atomic nuclei (the 'R-process') | T32: Because stellar fusion processes skip over them due to their position on the binding energy curve, making them harder to fuse | U32: No, because stardust only contains heavy metals and cannot form hydrogen | V32: They produce radiation that strips electrons from surrounding gas, promoting further star formation through collisions. | W32: The temperature rises until the outward kinetic energy of the gas balances the inward gravitational pull. | X32: Our home supercluster - Laniakea | Y32: Random energy spawnings caused matter to clump together, a pattern that magnified as the universe expanded. | Z32: B) A basin of attraction where the peculiar velocities of galaxies are directed inward toward a common gravitational focal point. | AA32: C) Cosmic voids, which are vast regions nearly empty of galaxies. | AB32: C) It does not interact via the electromagnetic force, meaning it neither emits, absorbs, nor reflects light. | AC32: B) It drives the accelerating, exponential expansion of the universe on large scales. | AD32: C) Modified Newtonian Dynamics | AE32: B) Gravitational energy released as the massive cloud of gas continuously contracts under its own weight. | AF32: B) Rapid rotation and convective currents drag the Lithium into the deep, hot interior of the star where it is destroyed by nuclear reactions. | AG32: D) The initiation of sustained hydrogen-to-helium nuclear fusion in the star's core. | AH32: C) They are formed during the cataclysmic explosions of supernovae and the violent mergers of neutron stars. | AI32: C) A black hole | AJ32: B) The creation of slightly more matter than antimatter (roughly one extra per billion), allowing the material universe to exist. | AK32: A) At your zenith (directly overhead). | AL32: C) Because the angle of the celestial pole correlates to the observer's latitude on the globe. | AM32: Long-press the constellations button in the bottom left and turn off the 'Centered Only' setting. | AN32: Tap the time in the bottom right, open the precise time controls, enter your birth date and time, and then locate the Moon. | AO32: Winter Solstice Sunset | AP32: The monsoon clouds heavily affect southern India, forcing observatories to shut down for months, whereas the Himalayan ranges block these clouds, providing consistently clear skies. | AQ32: It helps preserve the natural navigation cues for migratory birds, which can otherwise be easily confused by bright artificial lighting. | AR32: (1, 2, [3, 4, 5]) | AS32: [1, 2, 3, 4] | AT32: (1, 2) | AU32: 2 | AV32: [1, 2, 3] | AW32: 8 pattern | AX32: B) The sun obscures the summer solstice constellations during the summer, but during the winter, the night side of the Earth faces them. | AY32: A) They appear significantly stretched out horizontally compared to how they actually look in the night sky. | BA32: C) Mars | BB32: B) Because the light of non-point objects is spread over an area, which can make them appear dimmer than their total magnitude suggests.
A33: 46180.639 | B33: skm25ms251@iiserkol.ac.in | C33: 39 | D33: https://colab.research.google.com/drive/1cWO-okMgYgkVD-6XdxfyGQJUYUq7K4YL?usp=sharing | E33: =VALUE(LEFT(C33,FIND("/",C33)-1))+IF(D33<>"",5,0) -> 44 | F33: AE-0693 | G33: Sanidhya Kumar Mohanta | H33: skm25ms251@iiserkol.ac.in | I33: 8917299361 | J33: It would disprove the idea that the universe originated from a single point. | K33: The cooling of the universe allowed ionized nuclei to capture electrons, neutralizing their charge and stopping them from constantly scattering photons. | L33: The separation of the strong nuclear force from the electroweak force. | N33: A: Merger of two galaxies during early galaxy formation B: Death of a star | O33: It is the leftover light emitted by a hot, dense plasma that permeated the entire universe roughly 400,000 years after the Big Bang. | P33: The R-process involves rapid neutron accumulation before decay, leading to larger jumps in atomic mass compared to the slower S-process | R33: The universe is not infinitely old, meaning light from the most distant stars has simply not had enough time to reach us. | S33: The merger releases a massive amount of neutrons, which are then captured by atomic nuclei (the 'R-process') | T33: Because stellar fusion processes skip over them due to their position on the binding energy curve, making them harder to fuse | U33: Yes, because hydrogen and helium were primarily formed during the Big Bang which later went on to become stars where other elements were created. | V33: They produce radiation that strips electrons from surrounding gas, promoting further star formation through collisions. | W33: The temperature rises until the outward kinetic energy of the gas balances the inward gravitational pull. | X33: Our home supercluster - Laniakea | Y33: Random energy spawnings caused matter to clump together, a pattern that magnified as the universe expanded. | Z33: B) A basin of attraction where the peculiar velocities of galaxies are directed inward toward a common gravitational focal point. | AA33: C) Cosmic voids, which are vast regions nearly empty of galaxies. | AB33: C) It does not interact via the electromagnetic force, meaning it neither emits, absorbs, nor reflects light. | AC33: B) It drives the accelerating, exponential expansion of the universe on large scales. | AD33: C) Modified Newtonian Dynamics | AE33: B) Gravitational energy released as the massive cloud of gas continuously contracts under its own weight. | AF33: B) Rapid rotation and convective currents drag the Lithium into the deep, hot interior of the star where it is destroyed by nuclear reactions. | AG33: D) The initiation of sustained hydrogen-to-helium nuclear fusion in the star's core. | AH33: C) They are formed during the cataclysmic explosions of supernovae and the violent mergers of neutron stars. | AI33: C) A black hole | AJ33: B) The creation of slightly more matter than antimatter (roughly one extra per billion), allowing the material universe to exist. | AK33: A) At your zenith (directly overhead). | AL33: C) Because the angle of the celestial pole correlates to the observer's latitude on the globe. | AM33: Long-press the constellations button in the bottom left and turn off the 'Centered Only' setting. | AN33: Tap the time in the bottom right, open the precise time controls, enter your birth date and time, and then locate the Moon. | AO33: Equinox Sunrise | AP33: The monsoon clouds heavily affect southern India, forcing observatories to shut down for months, whereas the Himalayan ranges block these clouds, providing consistently clear skies. | AQ33: It helps preserve the natural navigation cues for migratory birds, which can otherwise be easily confused by bright artificial lighting. | AR33: (1, 2, [3, 4, 5]) | AS33: [1, 2, 3, 4] | AT33: (1, 2) | AU33: Error | AV33: [1, 2, 3] | AW33: ∞ pattrn | AX33: B) The sun obscures the summer solstice constellations during the summer, but during the winter, the night side of the Earth faces them. | AY33: A) They appear significantly stretched out horizontally compared to how they actually look in the night sky. | AZ33: B) Jupiter appears high in the dark night sky and is exceptionally bright, whereas Mercury is only visible very close to the horizon during sunrise or sunset and is often hidden by clouds. | BA33: C) Mars | BB33: B) Because the light of non-point objects is spread over an area, which can make them appear dimmer than their total magnitude suggests.
A34: 46180.798 | B34: bsnl007@gmail.com | C34: 33 | E34: =VALUE(LEFT(C34,FIND("/",C34)-1))+IF(D34<>"",5,0) -> 33 | F34: AE-0562 | G34: Ashaman Singh | H34: bsnl007@gmail.com | I34: 9412739243 | J34: It would confirm a cyclic universe model. | K34: The cooling of the universe allowed ionized nuclei to capture electrons, neutralizing their charge and stopping them from constantly scattering photons. | L34: The separation of the strong nuclear force from the electroweak force. | N34: A: Merger of two galaxies during early galaxy formation B: Black Hole Formation | O34: It is the leftover light emitted by a hot, dense plasma that permeated the entire universe roughly 400,000 years after the Big Bang. | P34: The R-process involves rapid neutron accumulation before decay, leading to larger jumps in atomic mass compared to the slower S-process | R34: The universe is not infinitely old, meaning light from the most distant stars has simply not had enough time to reach us. | S34: The merger releases a massive amount of neutrons, which are then captured by atomic nuclei (the 'R-process') | T34: Because stellar fusion processes skip over them due to their position on the binding energy curve, making them harder to fuse | U34: Yes, because hydrogen and helium were primarily formed during the Big Bang which later went on to become stars where other elements were created. | V34: They produce radiation that strips electrons from surrounding gas, promoting further star formation through collisions. | W34: The temperature rises until the outward kinetic energy of the gas balances the inward gravitational pull. | X34: Our home supercluster - Laniakea | Y34: Random energy spawnings caused matter to clump together, a pattern that magnified as the universe expanded. | Z34: B) A basin of attraction where the peculiar velocities of galaxies are directed inward toward a common gravitational focal point. | AA34: C) Cosmic voids, which are vast regions nearly empty of galaxies. | AB34: C) It does not interact via the electromagnetic force, meaning it neither emits, absorbs, nor reflects light. | AC34: A) It binds the outer edges of rotating galaxies together, preventing them from flying apart due to centrifugal forces. | AD34: C) Modified Newtonian Dynamics | AE34: B) Gravitational energy released as the massive cloud of gas continuously contracts under its own weight. | AG34: D) The initiation of sustained hydrogen-to-helium nuclear fusion in the star's core. | AH34: C) They are formed during the cataclysmic explosions of supernovae and the violent mergers of neutron stars. | AI34: C) A black hole | AJ34: B) The creation of slightly more matter than antimatter (roughly one extra per billion), allowing the material universe to exist. | AK34: A) At your zenith (directly overhead). | AL34: C) Because the angle of the celestial pole correlates to the observer's latitude on the globe. | AM34: Long-press the constellations button in the bottom left and turn off the 'Centered Only' setting. | AN34: Tap the time in the bottom right, open the precise time controls, enter your birth date and time, and then locate the Moon. | AO34: Equinox Sunrise | AP34: The monsoon clouds heavily affect southern India, forcing observatories to shut down for months, whereas the Himalayan ranges block these clouds, providing consistently clear skies. | AQ34: It helps preserve the natural navigation cues for migratory birds, which can otherwise be easily confused by bright artificial lighting. | AW34: 8 pattern | AX34: B) The sun obscures the summer solstice constellations during the summer, but during the winter, the night side of the Earth faces them. | AY34: A) They appear significantly stretched out horizontally compared to how they actually look in the night sky. | AZ34: B) Jupiter appears high in the dark night sky and is exceptionally bright, whereas Mercury is only visible very close to the horizon during sunrise or sunset and is often hidden by clouds. | BA34: C) Mars | BB34: B) Because the light of non-point objects is spread over an area, which can make them appear dimmer than their total magnitude suggests.
A35: 46180.807 | B35: ratnadipshaw2006@gmail.com | C35: 37 | D35: https://colab.research.google.com/drive/1XUHeVDAAvu_2s0LEcTRt1_35s96qieUk?usp=sharing | E35: =VALUE(LEFT(C35,FIND("/",C35)-1))+IF(D35<>"",5,0) -> 42 | F35: AE-0430 | G35: Ratnadip Shaw | H35: ratnadipshaw2006@gmail.com | I35: 7278433495 | J35: It would confirm a cyclic universe model. | K35: The cooling of the universe allowed ionized nuclei to capture electrons, neutralizing their charge and stopping them from constantly scattering photons. | L35: The separation of the strong nuclear force from the electroweak force. | N35: A: Merger of two galaxies during early galaxy formation B: Black Hole Formation | O35: It is the leftover light emitted by a hot, dense plasma that permeated the entire universe roughly 400,000 years after the Big Bang. | P35: The R-process involves rapid neutron accumulation before decay, leading to larger jumps in atomic mass compared to the slower S-process | R35: The universe is not infinitely old, meaning light from the most distant stars has simply not had enough time to reach us. | S35: The merger releases a massive amount of neutrons, which are then captured by atomic nuclei (the 'R-process') | T35: Because stars reach temperatures that immediately destroy these specific elements | U35: Yes, because hydrogen and helium were primarily formed during the Big Bang which later went on to become stars where other elements were created. | V35: They produce radiation that strips electrons from surrounding gas, promoting further star formation through collisions. | W35: The temperature rises until the outward kinetic energy of the gas balances the inward gravitational pull. | X35: Our home supercluster - Laniakea | Y35: Random energy spawnings caused matter to clump together, a pattern that magnified as the universe expanded. | Z35: B) A basin of attraction where the peculiar velocities of galaxies are directed inward toward a common gravitational focal point. | AA35: C) Cosmic voids, which are vast regions nearly empty of galaxies. | AB35: C) It does not interact via the electromagnetic force, meaning it neither emits, absorbs, nor reflects light. | AC35: B) It drives the accelerating, exponential expansion of the universe on large scales. | AD35: C) Modified Newtonian Dynamics | AE35: B) Gravitational energy released as the massive cloud of gas continuously contracts under its own weight. | AF35: B) Rapid rotation and convective currents drag the Lithium into the deep, hot interior of the star where it is destroyed by nuclear reactions. | AG35: D) The initiation of sustained hydrogen-to-helium nuclear fusion in the star's core. | AH35: C) They are formed during the cataclysmic explosions of supernovae and the violent mergers of neutron stars. | AI35: C) A black hole | AJ35: B) The creation of slightly more matter than antimatter (roughly one extra per billion), allowing the material universe to exist. | AK35: A) At your zenith (directly overhead). | AL35: C) Because the angle of the celestial pole correlates to the observer's latitude on the globe. | AM35: Long-press the constellations button in the bottom left and turn off the 'Centered Only' setting. | AN35: Tap the time in the bottom right, open the precise time controls, enter your birth date and time, and then locate the Moon. | AO35: Summer Solstice Sunrise | AP35: The monsoon clouds heavily affect southern India, forcing observatories to shut down for months, whereas the Himalayan ranges block these clouds, providing consistently clear skies. | AQ35: It helps preserve the natural navigation cues for migratory birds, which can otherwise be easily confused by bright artificial lighting. | AR35: (1, 2, [3, 4, 5]) | AS35: [1, 2, 3, 4] | AT35: (1, 2) | AU35: Error | AV35: [1, 2, 3] | AW35: ∞ pattrn | AX35: B) The sun obscures the summer solstice constellations during the summer, but during the winter, the night side of the Earth faces them. | AY35: A) They appear significantly stretched out horizontally compared to how they actually look in the night sky. | AZ35: B) Jupiter appears high in the dark night sky and is exceptionally bright, whereas Mercury is only visible very close to the horizon during sunrise or sunset and is often hidden by clouds. | BA35: C) Mars | BB35: B) Because the light of non-point objects is spread over an area, which can make them appear dimmer than their total magnitude suggests.
A36: 46180.817 | B36: krishna5604sharma@gmail.com | C36: 42 | E36: =VALUE(LEFT(C36,FIND("/",C36)-1))+IF(D36<>"",5,0) -> 42 | F36: AE-0987 | G36: Krishna Sharma | H36: krishna5064sharma@gmail.com | I36: 6398623932 | J36: It would disprove the idea that the universe originated from a single point. | K36: The cooling of the universe allowed ionized nuclei to capture electrons, neutralizing their charge and stopping them from constantly scattering photons. | L36: The separation of the strong nuclear force from the electroweak force. | N36: A: Merger of two galaxies during early galaxy formation B: Black Hole Formation | O36: It is the leftover light emitted by a hot, dense plasma that permeated the entire universe roughly 400,000 years after the Big Bang. | P36: The R-process involves rapid neutron accumulation before decay, leading to larger jumps in atomic mass compared to the slower S-process | R36: The universe is not infinitely old, meaning light from the most distant stars has simply not had enough time to reach us. | S36: The merger releases a massive amount of neutrons, which are then captured by atomic nuclei (the 'R-process') | T36: Because stellar fusion processes skip over them due to their position on the binding energy curve, making them harder to fuse | U36: No, because Only elements like carbon, oxygen, neon, silicon, iron, etc. are formed from stellar synthesis except which all other elements are not directly products of stardust. | V36: They produce radiation that strips electrons from surrounding gas, promoting further star formation through collisions. | W36: The temperature rises until the outward kinetic energy of the gas balances the inward gravitational pull. | X36: Our home supercluster - Laniakea | Y36: Random energy spawnings caused matter to clump together, a pattern that magnified as the universe expanded. | Z36: B) A basin of attraction where the peculiar velocities of galaxies are directed inward toward a common gravitational focal point. | AA36: C) Cosmic voids, which are vast regions nearly empty of galaxies. | AB36: C) It does not interact via the electromagnetic force, meaning it neither emits, absorbs, nor reflects light. | AC36: B) It drives the accelerating, exponential expansion of the universe on large scales. | AD36: C) Modified Newtonian Dynamics | AE36: B) Gravitational energy released as the massive cloud of gas continuously contracts under its own weight. | AF36: B) Rapid rotation and convective currents drag the Lithium into the deep, hot interior of the star where it is destroyed by nuclear reactions. | AG36: D) The initiation of sustained hydrogen-to-helium nuclear fusion in the star's core. | AH36: C) They are formed during the cataclysmic explosions of supernovae and the violent mergers of neutron stars. | AI36: C) A black hole | AJ36: B) The creation of slightly more matter than antimatter (roughly one extra per billion), allowing the material universe to exist. | AK36: A) At your zenith (directly overhead). | AL36: C) Because the angle of the celestial pole correlates to the observer's latitude on the globe. | AM36: Long-press the constellations button in the bottom left and turn off the 'Centered Only' setting. | AN36: Tap the time in the bottom right, open the precise time controls, enter your birth date and time, and then locate the Moon. | AO36: Equinox Sunrise | AP36: The monsoon clouds heavily affect southern India, forcing observatories to shut down for months, whereas the Himalayan ranges block these clouds, providing consistently clear skies. | AQ36: It helps preserve the natural navigation cues for migratory birds, which can otherwise be easily confused by bright artificial lighting. | AR36: (1, 2, [3, 4, 5]) | AS36: [1, 2, 3, 4] | AT36: (1, 2) | AU36: Error | AV36: [1, 2, 3] | AW36: 8 pattern | AX36: B) The sun obscures the summer solstice constellations during the summer, but during the winter, the night side of the Earth faces them. | AY36: A) They appear significantly stretched out horizontally compared to how they actually look in the night sky. | AZ36: B) Jupiter appears high in the dark night sky and is exceptionally bright, whereas Mercury is only visible very close to the horizon during sunrise or sunset and is often hidden by clouds. | BA36: C) Mars | BB36: B) Because the light of non-point objects is spread over an area, which can make them appear dimmer than their total magnitude suggests.
A37: 46180.831 | B37: bittukumarv248@gmail.com | C37: 39 | D37: https://colab.research.google.com/drive/1_haqKHp8k24l7qdb2eHyVqlBwS0KkUwu?usp=sharing | E37: =VALUE(LEFT(C37,FIND("/",C37)-1))+IF(D37<>"",5,0) -> 44 | F37: AE-0992 | G37: Bittu Kumar | H37: sanjeetkumar82137gmail.com | I37: 6204420339 | J37: It would disprove the idea that the universe originated from a single point. | K37: The cooling of the universe allowed ionized nuclei to capture electrons, neutralizing their charge and stopping them from constantly scattering photons. | L37: The separation of the strong nuclear force from the electroweak force. | N37: A: Merger of two galaxies during early galaxy formation B: Black Hole Formation | O37: It is the leftover light emitted by a hot, dense plasma that permeated the entire universe roughly 400,000 years after the Big Bang. | P37: The R-process involves rapid neutron accumulation before decay, leading to larger jumps in atomic mass compared to the slower S-process | R37: The universe is not infinitely old, meaning light from the most distant stars has simply not had enough time to reach us. | S37: By using gravitational waves to physically crush atoms into larger elements | T37: Because stellar fusion processes skip over them due to their position on the binding energy curve, making them harder to fuse | U37: Yes, because hydrogen and helium were primarily formed during the Big Bang which later went on to become stars where other elements were created. | V37: They produce radiation that strips electrons from surrounding gas, promoting further star formation through collisions. | W37: The temperature rises until the outward kinetic energy of the gas balances the inward gravitational pull. | X37: Our home supercluster - Laniakea | Y37: Random energy spawnings caused matter to clump together, a pattern that magnified as the universe expanded. | Z37: B) A basin of attraction where the peculiar velocities of galaxies are directed inward toward a common gravitational focal point. | AA37: C) Cosmic voids, which are vast regions nearly empty of galaxies. | AB37: C) It does not interact via the electromagnetic force, meaning it neither emits, absorbs, nor reflects light. | AC37: B) It drives the accelerating, exponential expansion of the universe on large scales. | AD37: C) Modified Newtonian Dynamics | AE37: B) Gravitational energy released as the massive cloud of gas continuously contracts under its own weight. | AF37: B) Rapid rotation and convective currents drag the Lithium into the deep, hot interior of the star where it is destroyed by nuclear reactions. | AG37: D) The initiation of sustained hydrogen-to-helium nuclear fusion in the star's core. | AH37: C) They are formed during the cataclysmic explosions of supernovae and the violent mergers of neutron stars. | AI37: C) A black hole | AJ37: B) The creation of slightly more matter than antimatter (roughly one extra per billion), allowing the material universe to exist. | AK37: A) At your zenith (directly overhead). | AL37: C) Because the angle of the celestial pole correlates to the observer's latitude on the globe. | AM37: Long-press the constellations button in the bottom left and turn off the 'Centered Only' setting. | AN37: Tap the time in the bottom right, open the precise time controls, enter your birth date and time, and then locate the Moon. | AO37: Equinox Sunrise | AP37: The monsoon clouds heavily affect southern India, forcing observatories to shut down for months, whereas the Himalayan ranges block these clouds, providing consistently clear skies. | AQ37: It helps preserve the natural navigation cues for migratory birds, which can otherwise be easily confused by bright artificial lighting. | AR37: (1, 2, [3, 4, 5]) | AS37: [1, 2, 3, 4] | AT37: (1, 2) | AU37: Error | AV37: [1, 2, 3] | AW37: ∞ pattrn | AX37: B) The sun obscures the summer solstice constellations during the summer, but during the winter, the night side of the Earth faces them. | AY37: A) They appear significantly stretched out horizontally compared to how they actually look in the night sky. | AZ37: B) Jupiter appears high in the dark night sky and is exceptionally bright, whereas Mercury is only visible very close to the horizon during sunrise or sunset and is often hidden by clouds. | BA37: C) Mars | BB37: B) Because the light of non-point objects is spread over an area, which can make them appear dimmer than their total magnitude suggests.
